{"kpi": {"leadTime": 67.88501026694045, "count": 1948.0, "price": 1397591.060606061, "dist": [34.1, 21.5, 13.9, 16.3, 7.9, 1.3, 2.2, 2.9]}, "dept": [{"name": "국내팀", "leadTime": 46.95238095238095, "count": 42.0, "price": 387769.2307692308, "dist": [40.5, 23.8, 9.5, 26.2, 0.0, 0.0, 0.0, 0.0]}, {"name": "남태평양팀", "leadTime": 44.36274509803921, "count": 102.0, "price": 1539988.222222222, "dist": [50.0, 34.3, 2.0, 5.9, 5.9, 0.0, 2.0, 0.0]}, {"name": "대구지점", "leadTime": 33.78571428571428, "count": 14.0, "price": 536955.5555555555, "dist": [50.0, 50.0, 0.0, 0.0, 0.0, 0.0, 0.0, 0.0]}, {"name": "동남아1팀", "leadTime": 58.2108843537415, "count": 294.0, "price": 617154.2395833334, "dist": [42.5, 23.1, 6.1, 13.3, 11.9, 2.0, 1.0, 0.0]}, {"name": "동남아2팀", "leadTime": 60.7578947368421, "count": 190.0, "price": 690963.4464285715, "dist": [35.3, 22.1, 8.9, 32.1, 0.5, 0.0, 1.1, 0.0]}, {"name": "동유럽팀", "leadTime": 76.90384615384616, "count": 104.0, "price": 3187740.964285714, "dist": [32.7, 14.4, 14.4, 21.2, 7.7, 0.0, 9.6, 0.0]}, {"name": "미주팀", "leadTime": 78.13333333333334, "count": 45.0, "price": 4282323.80952381, "dist": [15.6, 22.2, 17.8, 33.3, 6.7, 0.0, 4.4, 0.0]}, {"name": "부산지점", "leadTime": 51.32530120481928, "count": 166.0, "price": 791676.3490566037, "dist": [39.2, 22.9, 16.3, 21.7, 0.0, 0.0, 0.0, 0.0]}, {"name": "서유럽팀", "leadTime": 117.8181818181818, "count": 220.0, "price": 3298662.914893617, "dist": [11.8, 17.3, 16.8, 10.5, 15.5, 4.1, 9.1, 15.0]}, {"name": "스페인/북유럽팀", "leadTime": 103.3714285714286, "count": 105.0, "price": 2753995.277777778, "dist": [11.4, 24.8, 21.0, 11.4, 12.4, 1.9, 0.0, 17.1]}, {"name": "일본팀", "leadTime": 64.1304347826087, "count": 207.0, "price": 998816.1428571428, "dist": [33.8, 23.2, 18.8, 9.7, 11.6, 0.0, 0.0, 2.9]}, {"name": "중국팀", "leadTime": 56.72173913043478, "count": 230.0, "price": 869185.0285714286, "dist": [38.3, 19.6, 19.6, 13.5, 9.1, 0.0, 0.0, 0.0]}, {"name": "지중해/인도/아프리카팀", "leadTime": 69.94029850746269, "count": 67.0, "price": 1963472.727272727, "dist": [20.9, 34.3, 14.9, 20.9, 0.0, 3.0, 6.0, 0.0]}, {"name": "크루즈/테마팀", "leadTime": 113.0, "count": 3.0, "price": 0.0, "dist": [0.0, 0.0, 33.3, 0.0, 66.7, 0.0, 0.0, 0.0]}, {"name": "태국파트", "leadTime": 75.13513513513513, "count": 37.0, "price": 577750.0, "dist": [37.8, 5.4, 5.4, 40.5, 0.0, 10.8, 0.0, 0.0]}, {"name": "프리미엄팀", "leadTime": 91.76923076923077, "count": 13.0, "price": 9595933.333333334, "dist": [23.1, 0.0, 30.8, 15.4, 15.4, 15.4, 0.0, 0.0]}, {"name": "필리핀/말레이시아파트", "leadTime": 41.14678899082569, "count": 109.0, "price": 636883.5, "dist": [59.6, 10.1, 17.4, 9.2, 3.7, 0.0, 0.0, 0.0]}], "prod": [{"name": "AGI000", "dept": "크루즈/테마팀", "leadTime": 128.0, "count": 2.0, "price": 0.0, "dist": [0.0, 0.0, 0.0, 0.0, 100.0, 0.0, 0.0, 0.0]}, {"name": "APF008", "dept": "동남아1팀", "leadTime": 67.0, "count": 2.0, "price": 649000.0, "dist": [0.0, 0.0, 100.0, 0.0, 0.0, 0.0, 0.0, 0.0]}, {"name": "APF019", "dept": "동남아1팀", "leadTime": 30.66666666666667, "count": 6.0, "price": 872030.0, "dist": [33.3, 66.7, 0.0, 0.0, 0.0, 0.0, 0.0, 0.0]}, {"name": "APF0887", "dept": "필리핀/말레이시아파트", "leadTime": 79.0, "count": 1.0, "price": 480000.0, "dist": [0.0, 0.0, 100.0, 0.0, 0.0, 0.0, 0.0, 0.0]}, {"name": "APF7320", "dept": "동남아1팀", "leadTime": 29.63636363636364, "count": 11.0, "price": 1049000.0, "dist": [54.5, 45.5, 0.0, 0.0, 0.0, 0.0, 0.0, 0.0]}, {"name": "APF9695", "dept": "부산지점", "leadTime": 12.0, "count": 2.0, "price": 0.0, "dist": [100.0, 0.0, 0.0, 0.0, 0.0, 0.0, 0.0, 0.0]}, {"name": "APP0005", "dept": "태국파트", "leadTime": 90.47368421052632, "count": 19.0, "price": 439000.0, "dist": [26.3, 0.0, 10.5, 47.4, 0.0, 15.8, 0.0, 0.0]}, {"name": "APP0109", "dept": "동남아2팀", "leadTime": 194.0, "count": 2.0, "price": 1499000.0, "dist": [0.0, 0.0, 0.0, 0.0, 0.0, 0.0, 100.0, 0.0]}, {"name": "APP0233", "dept": "동남아1팀", "leadTime": 12.33333333333333, "count": 3.0, "price": 799000.0, "dist": [100.0, 0.0, 0.0, 0.0, 0.0, 0.0, 0.0, 0.0]}, {"name": "APP0237", "dept": "동남아1팀", "leadTime": 28.0625, "count": 16.0, "price": 824371.3571428572, "dist": [75.0, 12.5, 0.0, 12.5, 0.0, 0.0, 0.0, 0.0]}, {"name": "APP0277", "dept": "동남아1팀", "leadTime": 53.0, "count": 5.0, "price": 400000.0, "dist": [0.0, 100.0, 0.0, 0.0, 0.0, 0.0, 0.0, 0.0]}, {"name": "APP0288", "dept": "동남아1팀", "leadTime": 50.0, "count": 5.0, "price": 1559000.0, "dist": [0.0, 100.0, 0.0, 0.0, 0.0, 0.0, 0.0, 0.0]}, {"name": "APP0353", "dept": "태국파트", "leadTime": 96.0, "count": 2.0, "price": 0.0, "dist": [0.0, 0.0, 0.0, 100.0, 0.0, 0.0, 0.0, 0.0]}, {"name": "APP0388", "dept": "동남아1팀", "leadTime": 115.1111111111111, "count": 9.0, "price": 679170.0, "dist": [22.2, 0.0, 0.0, 11.1, 0.0, 66.7, 0.0, 0.0]}, {"name": "APP0397", "dept": "태국파트", "leadTime": 155.0, "count": 1.0, "price": 1109000.0, "dist": [0.0, 0.0, 0.0, 0.0, 0.0, 100.0, 0.0, 0.0]}, {"name": "APP0671", "dept": "필리핀/말레이시아파트", "leadTime": 39.0, "count": 4.0, "price": 0.0, "dist": [0.0, 100.0, 0.0, 0.0, 0.0, 0.0, 0.0, 0.0]}, {"name": "APP0681", "dept": "필리핀/말레이시아파트", "leadTime": 40.0, "count": 3.0, "price": 0.0, "dist": [0.0, 100.0, 0.0, 0.0, 0.0, 0.0, 0.0, 0.0]}, {"name": "APP0706", "dept": "동남아1팀", "leadTime": 67.75, "count": 8.0, "price": 849000.0, "dist": [0.0, 75.0, 0.0, 0.0, 25.0, 0.0, 0.0, 0.0]}, {"name": "APP0714", "dept": "동남아1팀", "leadTime": 98.0, "count": 3.0, "price": 1499000.0, "dist": [0.0, 0.0, 0.0, 100.0, 0.0, 0.0, 0.0, 0.0]}, {"name": "APP0715", "dept": "동남아1팀", "leadTime": 127.0, "count": 7.0, "price": 649000.0, "dist": [0.0, 0.0, 0.0, 0.0, 100.0, 0.0, 0.0, 0.0]}, {"name": "APP0748", "dept": "부산지점", "leadTime": 32.0, "count": 6.0, "price": 759000.0, "dist": [50.0, 50.0, 0.0, 0.0, 0.0, 0.0, 0.0, 0.0]}, {"name": "APP0764", "dept": "동남아1팀", "leadTime": 94.0, "count": 4.0, "price": 574000.0, "dist": [0.0, 0.0, 0.0, 100.0, 0.0, 0.0, 0.0, 0.0]}, {"name": "APP1100", "dept": "동남아2팀", "leadTime": 51.83333333333334, "count": 6.0, "price": 0.0, "dist": [66.7, 0.0, 0.0, 33.3, 0.0, 0.0, 0.0, 0.0]}, {"name": "APP1141", "dept": "동남아2팀", "leadTime": 16.0, "count": 2.0, "price": 1199000.0, "dist": [100.0, 0.0, 0.0, 0.0, 0.0, 0.0, 0.0, 0.0]}, {"name": "APP1142", "dept": "동남아2팀", "leadTime": 35.06666666666667, "count": 15.0, "price": 1649000.0, "dist": [46.7, 53.3, 0.0, 0.0, 0.0, 0.0, 0.0, 0.0]}, {"name": "APP1200", "dept": "동남아2팀", "leadTime": 69.0, "count": 4.0, "price": 699000.0, "dist": [0.0, 50.0, 0.0, 50.0, 0.0, 0.0, 0.0, 0.0]}, {"name": "APP1203", "dept": "동남아1팀", "leadTime": 81.0, "count": 2.0, "price": 0.0, "dist": [0.0, 0.0, 100.0, 0.0, 0.0, 0.0, 0.0, 0.0]}, {"name": "APP1291", "dept": "동남아1팀", "leadTime": 16.0, "count": 2.0, "price": 0.0, "dist": [100.0, 0.0, 0.0, 0.0, 0.0, 0.0, 0.0, 0.0]}, {"name": "APP1299", "dept": "동남아2팀", "leadTime": 70.29761904761905, "count": 84.0, "price": 661761.6071428572, "dist": [21.4, 22.6, 16.7, 39.3, 0.0, 0.0, 0.0, 0.0]}, {"name": "APP130", "dept": "동남아2팀", "leadTime": 25.22222222222222, "count": 9.0, "price": 405888.8888888889, "dist": [77.8, 22.2, 0.0, 0.0, 0.0, 0.0, 0.0, 0.0]}, {"name": "APP1309", "dept": "동남아1팀", "leadTime": 15.0, "count": 2.0, "price": 0.0, "dist": [100.0, 0.0, 0.0, 0.0, 0.0, 0.0, 0.0, 0.0]}, {"name": "APP1314", "dept": "동남아1팀", "leadTime": 28.21739130434782, "count": 46.0, "price": 529510.1785714285, "dist": [87.0, 4.3, 0.0, 8.7, 0.0, 0.0, 0.0, 0.0]}, {"name": "APP136", "dept": "동남아2팀", "leadTime": 46.05, "count": 40.0, "price": 596448.7058823529, "dist": [60.0, 5.0, 5.0, 30.0, 0.0, 0.0, 0.0, 0.0]}, {"name": "APP138", "dept": "동남아2팀", "leadTime": 15.0, "count": 1.0, "price": 0.0, "dist": [100.0, 0.0, 0.0, 0.0, 0.0, 0.0, 0.0, 0.0]}, {"name": "APP1489", "dept": "필리핀/말레이시아파트", "leadTime": 25.0, "count": 4.0, "price": 922430.0, "dist": [100.0, 0.0, 0.0, 0.0, 0.0, 0.0, 0.0, 0.0]}, {"name": "APP168", "dept": "동남아2팀", "leadTime": 36.0, "count": 4.0, "price": 0.0, "dist": [0.0, 100.0, 0.0, 0.0, 0.0, 0.0, 0.0, 0.0]}, {"name": "APP1991", "dept": "태국파트", "leadTime": 14.0, "count": 4.0, "price": 0.0, "dist": [100.0, 0.0, 0.0, 0.0, 0.0, 0.0, 0.0, 0.0]}, {"name": "APP234", "dept": "동남아2팀", "leadTime": 28.0, "count": 2.0, "price": 1199000.0, "dist": [100.0, 0.0, 0.0, 0.0, 0.0, 0.0, 0.0, 0.0]}, {"name": "APP2448", "dept": "동남아1팀", "leadTime": 99.66666666666667, "count": 3.0, "price": 999000.0, "dist": [0.0, 0.0, 0.0, 100.0, 0.0, 0.0, 0.0, 0.0]}, {"name": "APP2625", "dept": "동남아1팀", "leadTime": 93.85714285714286, "count": 28.0, "price": 474000.0, "dist": [14.3, 7.1, 7.1, 53.6, 7.1, 0.0, 10.7, 0.0]}, {"name": "APP2666", "dept": "동남아1팀", "leadTime": 18.0, "count": 2.0, "price": 387030.0, "dist": [100.0, 0.0, 0.0, 0.0, 0.0, 0.0, 0.0, 0.0]}, {"name": "APP3375", "dept": "동남아1팀", "leadTime": 35.9, "count": 10.0, "price": 715666.6666666666, "dist": [30.0, 70.0, 0.0, 0.0, 0.0, 0.0, 0.0, 0.0]}, {"name": "APP3502", "dept": "필리핀/말레이시아파트", "leadTime": 30.58823529411765, "count": 17.0, "price": 244538.4615384615, "dist": [76.5, 0.0, 23.5, 0.0, 0.0, 0.0, 0.0, 0.0]}, {"name": "APP4120", "dept": "필리핀/말레이시아파트", "leadTime": 102.0, "count": 4.0, "price": 0.0, "dist": [0.0, 0.0, 0.0, 100.0, 0.0, 0.0, 0.0, 0.0]}, {"name": "APP4330", "dept": "필리핀/말레이시아파트", "leadTime": 1.0, "count": 4.0, "price": 649000.0, "dist": [100.0, 0.0, 0.0, 0.0, 0.0, 0.0, 0.0, 0.0]}, {"name": "APP4417", "dept": "태국파트", "leadTime": 39.0, "count": 2.0, "price": 0.0, "dist": [0.0, 100.0, 0.0, 0.0, 0.0, 0.0, 0.0, 0.0]}, {"name": "APP4499", "dept": "필리핀/말레이시아파트", "leadTime": 27.0, "count": 4.0, "price": 969000.0, "dist": [100.0, 0.0, 0.0, 0.0, 0.0, 0.0, 0.0, 0.0]}, {"name": "APP4568", "dept": "필리핀/말레이시아파트", "leadTime": 35.0, "count": 3.0, "price": 0.0, "dist": [0.0, 100.0, 0.0, 0.0, 0.0, 0.0, 0.0, 0.0]}, {"name": "APP4652", "dept": "필리핀/말레이시아파트", "leadTime": 4.0, "count": 4.0, "price": 226600.0, "dist": [100.0, 0.0, 0.0, 0.0, 0.0, 0.0, 0.0, 0.0]}, {"name": "APP4661", "dept": "필리핀/말레이시아파트", "leadTime": 57.2, "count": 5.0, "price": 637708.0, "dist": [40.0, 0.0, 60.0, 0.0, 0.0, 0.0, 0.0, 0.0]}, {"name": "APP4920", "dept": "필리핀/말레이시아파트", "leadTime": 16.0, "count": 3.0, "price": 569000.0, "dist": [100.0, 0.0, 0.0, 0.0, 0.0, 0.0, 0.0, 0.0]}, {"name": "APP4991", "dept": "필리핀/말레이시아파트", "leadTime": 86.2, "count": 5.0, "price": 564200.0, "dist": [0.0, 20.0, 0.0, 80.0, 0.0, 0.0, 0.0, 0.0]}, {"name": "APP5131", "dept": "동남아2팀", "leadTime": 69.0, "count": 1.0, "price": 0.0, "dist": [0.0, 0.0, 100.0, 0.0, 0.0, 0.0, 0.0, 0.0]}, {"name": "APP5141", "dept": "동남아2팀", "leadTime": 36.0, "count": 3.0, "price": 0.0, "dist": [0.0, 100.0, 0.0, 0.0, 0.0, 0.0, 0.0, 0.0]}, {"name": "APP5157", "dept": "동남아1팀", "leadTime": 80.0, "count": 2.0, "price": 249000.0, "dist": [0.0, 0.0, 100.0, 0.0, 0.0, 0.0, 0.0, 0.0]}, {"name": "APP5211", "dept": "동남아1팀", "leadTime": 56.96296296296296, "count": 27.0, "price": 340529.4117647059, "dist": [22.2, 51.9, 7.4, 3.7, 14.8, 0.0, 0.0, 0.0]}, {"name": "APP5259", "dept": "동남아1팀", "leadTime": 42.90909090909091, "count": 22.0, "price": 340135.0, "dist": [45.5, 36.4, 9.1, 9.1, 0.0, 0.0, 0.0, 0.0]}, {"name": "APP5368", "dept": "동남아1팀", "leadTime": 90.14634146341463, "count": 41.0, "price": 592540.5405405406, "dist": [31.7, 19.5, 0.0, 0.0, 48.8, 0.0, 0.0, 0.0]}, {"name": "APP5377", "dept": "동남아1팀", "leadTime": 24.0, "count": 4.0, "price": 879000.0, "dist": [100.0, 0.0, 0.0, 0.0, 0.0, 0.0, 0.0, 0.0]}, {"name": "APP5380", "dept": "동남아1팀", "leadTime": 54.33333333333334, "count": 3.0, "price": 515733.3333333333, "dist": [33.3, 0.0, 66.7, 0.0, 0.0, 0.0, 0.0, 0.0]}, {"name": "APP5400", "dept": "동남아2팀", "leadTime": 28.0, "count": 2.0, "price": 0.0, "dist": [100.0, 0.0, 0.0, 0.0, 0.0, 0.0, 0.0, 0.0]}, {"name": "APP5440", "dept": "동남아2팀", "leadTime": 114.5384615384615, "count": 13.0, "price": 609000.0, "dist": [0.0, 0.0, 0.0, 92.3, 7.7, 0.0, 0.0, 0.0]}, {"name": "APP5621", "dept": "필리핀/말레이시아파트", "leadTime": 8.0, "count": 4.0, "price": 606178.0, "dist": [100.0, 0.0, 0.0, 0.0, 0.0, 0.0, 0.0, 0.0]}, {"name": "APP5624", "dept": "필리핀/말레이시아파트", "leadTime": 10.0, "count": 3.0, "price": 439333.3333333333, "dist": [100.0, 0.0, 0.0, 0.0, 0.0, 0.0, 0.0, 0.0]}, {"name": "APP5999", "dept": "필리핀/말레이시아파트", "leadTime": 25.1, "count": 10.0, "price": 615666.6666666666, "dist": [100.0, 0.0, 0.0, 0.0, 0.0, 0.0, 0.0, 0.0]}, {"name": "APP6366", "dept": "동남아1팀", "leadTime": 13.0, "count": 4.0, "price": 260000.0, "dist": [100.0, 0.0, 0.0, 0.0, 0.0, 0.0, 0.0, 0.0]}, {"name": "APP6400", "dept": "동남아1팀", "leadTime": 72.0, "count": 2.0, "price": 0.0, "dist": [0.0, 0.0, 100.0, 0.0, 0.0, 0.0, 0.0, 0.0]}, {"name": "APP6902", "dept": "필리핀/말레이시아파트", "leadTime": 10.0, "count": 2.0, "price": 669000.0, "dist": [100.0, 0.0, 0.0, 0.0, 0.0, 0.0, 0.0, 0.0]}, {"name": "APP7018", "dept": "태국파트", "leadTime": 20.0, "count": 5.0, "price": 659000.0, "dist": [100.0, 0.0, 0.0, 0.0, 0.0, 0.0, 0.0, 0.0]}, {"name": "APP7027", "dept": "태국파트", "leadTime": 120.0, "count": 4.0, "price": 0.0, "dist": [0.0, 0.0, 0.0, 100.0, 0.0, 0.0, 0.0, 0.0]}, {"name": "APP7111", "dept": "동남아1팀", "leadTime": 93.0, "count": 4.0, "price": 0.0, "dist": [0.0, 0.0, 0.0, 100.0, 0.0, 0.0, 0.0, 0.0]}, {"name": "APP7143", "dept": "동남아2팀", "leadTime": 50.0, "count": 2.0, "price": 0.0, "dist": [0.0, 100.0, 0.0, 0.0, 0.0, 0.0, 0.0, 0.0]}, {"name": "APP7233", "dept": "동남아1팀", "leadTime": 20.0, "count": 4.0, "price": 0.0, "dist": [100.0, 0.0, 0.0, 0.0, 0.0, 0.0, 0.0, 0.0]}, {"name": "APP7446", "dept": "필리핀/말레이시아파트", "leadTime": 131.0, "count": 4.0, "price": 0.0, "dist": [0.0, 0.0, 0.0, 0.0, 100.0, 0.0, 0.0, 0.0]}, {"name": "APP7483", "dept": "필리핀/말레이시아파트", "leadTime": 56.14285714285715, "count": 21.0, "price": 1209100.0, "dist": [38.1, 0.0, 52.4, 9.5, 0.0, 0.0, 0.0, 0.0]}, {"name": "APP8007", "dept": "필리핀/말레이시아파트", "leadTime": 17.0, "count": 4.0, "price": 580407.5, "dist": [100.0, 0.0, 0.0, 0.0, 0.0, 0.0, 0.0, 0.0]}, {"name": "APP879", "dept": "부산지점", "leadTime": 41.0, "count": 6.0, "price": 1129000.0, "dist": [0.0, 100.0, 0.0, 0.0, 0.0, 0.0, 0.0, 0.0]}, {"name": "APP9162", "dept": "부산지점", "leadTime": 17.0, "count": 1.0, "price": 0.0, "dist": [100.0, 0.0, 0.0, 0.0, 0.0, 0.0, 0.0, 0.0]}, {"name": "APP9204", "dept": "부산지점", "leadTime": 16.0, "count": 4.0, "price": 779000.0, "dist": [100.0, 0.0, 0.0, 0.0, 0.0, 0.0, 0.0, 0.0]}, {"name": "APP9274", "dept": "대구지점", "leadTime": 56.5, "count": 4.0, "price": 659000.0, "dist": [0.0, 100.0, 0.0, 0.0, 0.0, 0.0, 0.0, 0.0]}, {"name": "APP9547", "dept": "부산지점", "leadTime": 22.0, "count": 2.0, "price": 0.0, "dist": [100.0, 0.0, 0.0, 0.0, 0.0, 0.0, 0.0, 0.0]}, {"name": "APP9599", "dept": "부산지점", "leadTime": 26.08333333333333, "count": 12.0, "price": 389180.0, "dist": [100.0, 0.0, 0.0, 0.0, 0.0, 0.0, 0.0, 0.0]}, {"name": "APP9636", "dept": "동남아1팀", "leadTime": 34.71428571428572, "count": 7.0, "price": 320428.5714285714, "dist": [71.4, 0.0, 28.6, 0.0, 0.0, 0.0, 0.0, 0.0]}, {"name": "APP9661", "dept": "부산지점", "leadTime": 24.5, "count": 4.0, "price": 224200.0, "dist": [50.0, 50.0, 0.0, 0.0, 0.0, 0.0, 0.0, 0.0]}, {"name": "APP9692", "dept": "부산지점", "leadTime": 16.0, "count": 3.0, "price": 350000.0, "dist": [100.0, 0.0, 0.0, 0.0, 0.0, 0.0, 0.0, 0.0]}, {"name": "APP9945", "dept": "부산지점", "leadTime": 71.57894736842105, "count": 19.0, "price": 578550.0, "dist": [21.1, 21.1, 0.0, 57.9, 0.0, 0.0, 0.0, 0.0]}, {"name": "APP9947", "dept": "부산지점", "leadTime": 16.0, "count": 3.0, "price": 1267000.0, "dist": [100.0, 0.0, 0.0, 0.0, 0.0, 0.0, 0.0, 0.0]}, {"name": "APPT201", "dept": "대구지점", "leadTime": 21.0, "count": 2.0, "price": 639000.0, "dist": [100.0, 0.0, 0.0, 0.0, 0.0, 0.0, 0.0, 0.0]}, {"name": "CPP1008", "dept": "중국팀", "leadTime": 96.4, "count": 15.0, "price": 342428.5714285714, "dist": [0.0, 0.0, 0.0, 100.0, 0.0, 0.0, 0.0, 0.0]}, {"name": "CPP108", "dept": "중국팀", "leadTime": 64.0, "count": 2.0, "price": 0.0, "dist": [0.0, 0.0, 100.0, 0.0, 0.0, 0.0, 0.0, 0.0]}, {"name": "CPP163", "dept": "중국팀", "leadTime": 87.5, "count": 8.0, "price": 1832333.333333333, "dist": [50.0, 0.0, 0.0, 0.0, 50.0, 0.0, 0.0, 0.0]}, {"name": "CPP194", "dept": "중국팀", "leadTime": 51.0, "count": 2.0, "price": 299000.0, "dist": [0.0, 100.0, 0.0, 0.0, 0.0, 0.0, 0.0, 0.0]}, {"name": "CPP195", "dept": "중국팀", "leadTime": 23.0, "count": 2.0, "price": 0.0, "dist": [100.0, 0.0, 0.0, 0.0, 0.0, 0.0, 0.0, 0.0]}, {"name": "CPP255", "dept": "중국팀", "leadTime": 70.16666666666667, "count": 12.0, "price": 1119000.0, "dist": [0.0, 50.0, 16.7, 33.3, 0.0, 0.0, 0.0, 0.0]}, {"name": "CPP256", "dept": "중국팀", "leadTime": 19.0, "count": 2.0, "price": 899000.0, "dist": [100.0, 0.0, 0.0, 0.0, 0.0, 0.0, 0.0, 0.0]}, {"name": "CPP257", "dept": "중국팀", "leadTime": 41.33333333333334, "count": 6.0, "price": 0.0, "dist": [0.0, 100.0, 0.0, 0.0, 0.0, 0.0, 0.0, 0.0]}, {"name": "CPP276", "dept": "중국팀", "leadTime": 12.0, "count": 1.0, "price": 0.0, "dist": [100.0, 0.0, 0.0, 0.0, 0.0, 0.0, 0.0, 0.0]}, {"name": "CPP285", "dept": "중국팀", "leadTime": 18.0, "count": 2.0, "price": 599000.0, "dist": [100.0, 0.0, 0.0, 0.0, 0.0, 0.0, 0.0, 0.0]}, {"name": "CPP286", "dept": "중국팀", "leadTime": 65.5, "count": 20.0, "price": 699000.0, "dist": [10.0, 50.0, 40.0, 0.0, 0.0, 0.0, 0.0, 0.0]}, {"name": "CPP301", "dept": "중국팀", "leadTime": 80.25, "count": 8.0, "price": 1249000.0, "dist": [0.0, 62.5, 0.0, 37.5, 0.0, 0.0, 0.0, 0.0]}, {"name": "CPP303", "dept": "중국팀", "leadTime": 48.14285714285715, "count": 7.0, "price": 1496142.857142857, "dist": [42.9, 28.6, 28.6, 0.0, 0.0, 0.0, 0.0, 0.0]}, {"name": "CPP322", "dept": "중국팀", "leadTime": 46.66666666666666, "count": 9.0, "price": 649000.0, "dist": [55.6, 0.0, 44.4, 0.0, 0.0, 0.0, 0.0, 0.0]}, {"name": "CPP3232", "dept": "중국팀", "leadTime": 33.64705882352941, "count": 34.0, "price": 364909.6774193548, "dist": [58.8, 5.9, 35.3, 0.0, 0.0, 0.0, 0.0, 0.0]}, {"name": "CPP328", "dept": "중국팀", "leadTime": 23.0, "count": 2.0, "price": 0.0, "dist": [100.0, 0.0, 0.0, 0.0, 0.0, 0.0, 0.0, 0.0]}, {"name": "CPP333", "dept": "중국팀", "leadTime": 103.7777777777778, "count": 9.0, "price": 1565777.777777778, "dist": [0.0, 11.1, 22.2, 0.0, 66.7, 0.0, 0.0, 0.0]}, {"name": "CPP3400", "dept": "중국팀", "leadTime": 44.12, "count": 25.0, "price": 505245.8181818182, "dist": [60.0, 16.0, 8.0, 16.0, 0.0, 0.0, 0.0, 0.0]}, {"name": "CPP3500", "dept": "중국팀", "leadTime": 27.0, "count": 4.0, "price": 0.0, "dist": [100.0, 0.0, 0.0, 0.0, 0.0, 0.0, 0.0, 0.0]}, {"name": "CPP3700", "dept": "중국팀", "leadTime": 16.0, "count": 2.0, "price": 0.0, "dist": [100.0, 0.0, 0.0, 0.0, 0.0, 0.0, 0.0, 0.0]}, {"name": "CPP375", "dept": "중국팀", "leadTime": 38.66666666666666, "count": 6.0, "price": 712500.0, "dist": [66.7, 0.0, 33.3, 0.0, 0.0, 0.0, 0.0, 0.0]}, {"name": "CPP410", "dept": "중국팀", "leadTime": 26.0, "count": 1.0, "price": 779000.0, "dist": [100.0, 0.0, 0.0, 0.0, 0.0, 0.0, 0.0, 0.0]}, {"name": "CPP430", "dept": "중국팀", "leadTime": 125.0, "count": 8.0, "price": 0.0, "dist": [0.0, 0.0, 0.0, 0.0, 100.0, 0.0, 0.0, 0.0]}, {"name": "CPP431", "dept": "중국팀", "leadTime": 125.0, "count": 3.0, "price": 1349000.0, "dist": [0.0, 0.0, 0.0, 0.0, 100.0, 0.0, 0.0, 0.0]}, {"name": "CPP440", "dept": "중국팀", "leadTime": 14.0, "count": 1.0, "price": 0.0, "dist": [100.0, 0.0, 0.0, 0.0, 0.0, 0.0, 0.0, 0.0]}, {"name": "CPP4577", "dept": "중국팀", "leadTime": 32.0, "count": 2.0, "price": 0.0, "dist": [0.0, 100.0, 0.0, 0.0, 0.0, 0.0, 0.0, 0.0]}, {"name": "CPP4578", "dept": "중국팀", "leadTime": 69.0, "count": 4.0, "price": 199000.0, "dist": [0.0, 0.0, 100.0, 0.0, 0.0, 0.0, 0.0, 0.0]}, {"name": "CPP4753", "dept": "중국팀", "leadTime": 99.0, "count": 3.0, "price": 0.0, "dist": [0.0, 0.0, 0.0, 100.0, 0.0, 0.0, 0.0, 0.0]}, {"name": "CPP4762", "dept": "중국팀", "leadTime": 20.0, "count": 4.0, "price": 1299000.0, "dist": [100.0, 0.0, 0.0, 0.0, 0.0, 0.0, 0.0, 0.0]}, {"name": "CPP4765", "dept": "중국팀", "leadTime": 33.0, "count": 3.0, "price": 1499000.0, "dist": [0.0, 100.0, 0.0, 0.0, 0.0, 0.0, 0.0, 0.0]}, {"name": "CPP4768", "dept": "중국팀", "leadTime": 28.0, "count": 4.0, "price": 2099000.0, "dist": [100.0, 0.0, 0.0, 0.0, 0.0, 0.0, 0.0, 0.0]}, {"name": "CPP4777", "dept": "중국팀", "leadTime": 72.0, "count": 3.0, "price": 999000.0, "dist": [0.0, 0.0, 100.0, 0.0, 0.0, 0.0, 0.0, 0.0]}, {"name": "CPP521", "dept": "중국팀", "leadTime": 22.8, "count": 5.0, "price": 0.0, "dist": [60.0, 40.0, 0.0, 0.0, 0.0, 0.0, 0.0, 0.0]}, {"name": "CPP554", "dept": "중국팀", "leadTime": 106.0, "count": 1.0, "price": 0.0, "dist": [0.0, 0.0, 0.0, 100.0, 0.0, 0.0, 0.0, 0.0]}, {"name": "CPP760", "dept": "중국팀", "leadTime": 13.0, "count": 2.0, "price": 0.0, "dist": [100.0, 0.0, 0.0, 0.0, 0.0, 0.0, 0.0, 0.0]}, {"name": "CPP817", "dept": "부산지점", "leadTime": 17.0, "count": 2.0, "price": 0.0, "dist": [100.0, 0.0, 0.0, 0.0, 0.0, 0.0, 0.0, 0.0]}, {"name": "CPP819", "dept": "부산지점", "leadTime": 53.0, "count": 7.0, "price": 597857.1428571428, "dist": [28.6, 0.0, 71.4, 0.0, 0.0, 0.0, 0.0, 0.0]}, {"name": "CPP843", "dept": "중국팀", "leadTime": 17.0, "count": 2.0, "price": 0.0, "dist": [100.0, 0.0, 0.0, 0.0, 0.0, 0.0, 0.0, 0.0]}, {"name": "CPP898", "dept": "중국팀", "leadTime": 11.0, "count": 3.0, "price": 0.0, "dist": [100.0, 0.0, 0.0, 0.0, 0.0, 0.0, 0.0, 0.0]}, {"name": "CPP917", "dept": "부산지점", "leadTime": 85.0, "count": 4.0, "price": 1401622.5, "dist": [0.0, 0.0, 100.0, 0.0, 0.0, 0.0, 0.0, 0.0]}, {"name": "CPP929", "dept": "부산지점", "leadTime": 82.0, "count": 1.0, "price": 0.0, "dist": [0.0, 0.0, 100.0, 0.0, 0.0, 0.0, 0.0, 0.0]}, {"name": "CPP9376", "dept": "대구지점", "leadTime": 8.0, "count": 2.0, "price": 0.0, "dist": [100.0, 0.0, 0.0, 0.0, 0.0, 0.0, 0.0, 0.0]}, {"name": "CPP9605", "dept": "부산지점", "leadTime": 57.0, "count": 2.0, "price": 0.0, "dist": [0.0, 100.0, 0.0, 0.0, 0.0, 0.0, 0.0, 0.0]}, {"name": "CPP988", "dept": "부산지점", "leadTime": 50.14285714285715, "count": 28.0, "price": 785080.0, "dist": [53.6, 14.3, 0.0, 32.1, 0.0, 0.0, 0.0, 0.0]}, {"name": "CPP989", "dept": "부산지점", "leadTime": 102.5833333333333, "count": 12.0, "price": 1399833.333333333, "dist": [0.0, 0.0, 0.0, 100.0, 0.0, 0.0, 0.0, 0.0]}, {"name": "CPP9902", "dept": "부산지점", "leadTime": 38.5, "count": 2.0, "price": 1199000.0, "dist": [50.0, 50.0, 0.0, 0.0, 0.0, 0.0, 0.0, 0.0]}, {"name": "CPPT404", "dept": "대구지점", "leadTime": 6.0, "count": 1.0, "price": 0.0, "dist": [100.0, 0.0, 0.0, 0.0, 0.0, 0.0, 0.0, 0.0]}, {"name": "CPPT701", "dept": "대구지점", "leadTime": 15.0, "count": 2.0, "price": 819800.0, "dist": [100.0, 0.0, 0.0, 0.0, 0.0, 0.0, 0.0, 0.0]}, {"name": "EPM066", "dept": "크루즈/테마팀", "leadTime": 83.0, "count": 1.0, "price": 0.0, "dist": [0.0, 0.0, 100.0, 0.0, 0.0, 0.0, 0.0, 0.0]}, {"name": "EPP0071", "dept": "프리미엄팀", "leadTime": 28.0, "count": 2.0, "price": 4426100.0, "dist": [100.0, 0.0, 0.0, 0.0, 0.0, 0.0, 0.0, 0.0]}, {"name": "EPP0112", "dept": "스페인/북유럽팀", "leadTime": 30.5, "count": 4.0, "price": 4861600.0, "dist": [50.0, 50.0, 0.0, 0.0, 0.0, 0.0, 0.0, 0.0]}, {"name": "EPP0116", "dept": "스페인/북유럽팀", "leadTime": 25.0, "count": 2.0, "price": 3900000.0, "dist": [100.0, 0.0, 0.0, 0.0, 0.0, 0.0, 0.0, 0.0]}, {"name": "EPP021", "dept": "스페인/북유럽팀", "leadTime": 48.5, "count": 4.0, "price": 4535000.0, "dist": [0.0, 100.0, 0.0, 0.0, 0.0, 0.0, 0.0, 0.0]}, {"name": "EPP0211", "dept": "스페인/북유럽팀", "leadTime": 7.5, "count": 2.0, "price": 3390000.0, "dist": [100.0, 0.0, 0.0, 0.0, 0.0, 0.0, 0.0, 0.0]}, {"name": "EPP023", "dept": "스페인/북유럽팀", "leadTime": 41.0, "count": 5.0, "price": 4896300.0, "dist": [0.0, 100.0, 0.0, 0.0, 0.0, 0.0, 0.0, 0.0]}, {"name": "EPP027", "dept": "스페인/북유럽팀", "leadTime": 52.66666666666666, "count": 3.0, "price": 4830000.0, "dist": [0.0, 100.0, 0.0, 0.0, 0.0, 0.0, 0.0, 0.0]}, {"name": "EPP033", "dept": "스페인/북유럽팀", "leadTime": 28.0, "count": 1.0, "price": 6604300.0, "dist": [100.0, 0.0, 0.0, 0.0, 0.0, 0.0, 0.0, 0.0]}, {"name": "EPP035", "dept": "스페인/북유럽팀", "leadTime": 55.0, "count": 1.0, "price": 0.0, "dist": [0.0, 100.0, 0.0, 0.0, 0.0, 0.0, 0.0, 0.0]}, {"name": "EPP1121", "dept": "프리미엄팀", "leadTime": 159.0, "count": 2.0, "price": 16071700.0, "dist": [0.0, 0.0, 0.0, 0.0, 0.0, 100.0, 0.0, 0.0]}, {"name": "EPP208", "dept": "지중해/인도/아프리카팀", "leadTime": 79.75, "count": 8.0, "price": 1572333.333333333, "dist": [25.0, 25.0, 0.0, 25.0, 0.0, 25.0, 0.0, 0.0]}, {"name": "EPP214", "dept": "지중해/인도/아프리카팀", "leadTime": 43.0, "count": 3.0, "price": 0.0, "dist": [0.0, 100.0, 0.0, 0.0, 0.0, 0.0, 0.0, 0.0]}, {"name": "EPP2210", "dept": "지중해/인도/아프리카팀", "leadTime": 26.0, "count": 4.0, "price": 979000.0, "dist": [100.0, 0.0, 0.0, 0.0, 0.0, 0.0, 0.0, 0.0]}, {"name": "EPP2211", "dept": "지중해/인도/아프리카팀", "leadTime": 34.8, "count": 5.0, "price": 0.0, "dist": [40.0, 60.0, 0.0, 0.0, 0.0, 0.0, 0.0, 0.0]}, {"name": "EPP2370", "dept": "지중해/인도/아프리카팀", "leadTime": 63.0, "count": 4.0, "price": 3440650.0, "dist": [50.0, 0.0, 0.0, 50.0, 0.0, 0.0, 0.0, 0.0]}, {"name": "EPP2502", "dept": "프리미엄팀", "leadTime": 124.0, "count": 2.0, "price": 0.0, "dist": [0.0, 0.0, 0.0, 0.0, 100.0, 0.0, 0.0, 0.0]}, {"name": "EPP2547", "dept": "지중해/인도/아프리카팀", "leadTime": 56.0, "count": 2.0, "price": 0.0, "dist": [0.0, 100.0, 0.0, 0.0, 0.0, 0.0, 0.0, 0.0]}, {"name": "EPP2700", "dept": "지중해/인도/아프리카팀", "leadTime": 24.0, "count": 2.0, "price": 1595000.0, "dist": [100.0, 0.0, 0.0, 0.0, 0.0, 0.0, 0.0, 0.0]}, {"name": "EPP278", "dept": "지중해/인도/아프리카팀", "leadTime": 98.5, "count": 4.0, "price": 0.0, "dist": [0.0, 0.0, 0.0, 100.0, 0.0, 0.0, 0.0, 0.0]}, {"name": "EPP3046", "dept": "서유럽팀", "leadTime": 14.0, "count": 2.0, "price": 0.0, "dist": [100.0, 0.0, 0.0, 0.0, 0.0, 0.0, 0.0, 0.0]}, {"name": "EPP3049", "dept": "서유럽팀", "leadTime": 95.5, "count": 10.0, "price": 5236600.0, "dist": [20.0, 30.0, 10.0, 20.0, 0.0, 0.0, 0.0, 20.0]}, {"name": "EPP3097", "dept": "서유럽팀", "leadTime": 40.0, "count": 3.0, "price": 0.0, "dist": [0.0, 100.0, 0.0, 0.0, 0.0, 0.0, 0.0, 0.0]}, {"name": "EPP3116", "dept": "서유럽팀", "leadTime": 135.6666666666667, "count": 6.0, "price": 3853500.0, "dist": [0.0, 0.0, 0.0, 0.0, 100.0, 0.0, 0.0, 0.0]}, {"name": "EPP3145", "dept": "서유럽팀", "leadTime": 98.375, "count": 8.0, "price": 3803571.428571429, "dist": [25.0, 0.0, 0.0, 37.5, 25.0, 12.5, 0.0, 0.0]}, {"name": "EPP3147", "dept": "서유럽팀", "leadTime": 97.0, "count": 2.0, "price": 0.0, "dist": [0.0, 0.0, 0.0, 100.0, 0.0, 0.0, 0.0, 0.0]}, {"name": "EPP316", "dept": "서유럽팀", "leadTime": 63.5, "count": 12.0, "price": 3603600.0, "dist": [25.0, 50.0, 0.0, 0.0, 25.0, 0.0, 0.0, 0.0]}, {"name": "EPP3160", "dept": "서유럽팀", "leadTime": 45.0, "count": 2.0, "price": 0.0, "dist": [0.0, 100.0, 0.0, 0.0, 0.0, 0.0, 0.0, 0.0]}, {"name": "EPP3168", "dept": "서유럽팀", "leadTime": 193.2, "count": 35.0, "price": 2555384.615384615, "dist": [0.0, 0.0, 0.0, 11.4, 11.4, 0.0, 42.9, 34.3]}, {"name": "EPP3226", "dept": "프리미엄팀", "leadTime": 116.0, "count": 2.0, "price": 0.0, "dist": [0.0, 0.0, 0.0, 100.0, 0.0, 0.0, 0.0, 0.0]}, {"name": "EPP3270", "dept": "서유럽팀", "leadTime": 83.0, "count": 2.0, "price": 0.0, "dist": [0.0, 0.0, 100.0, 0.0, 0.0, 0.0, 0.0, 0.0]}, {"name": "EPP340", "dept": "서유럽팀", "leadTime": 38.5, "count": 4.0, "price": 3712000.0, "dist": [50.0, 50.0, 0.0, 0.0, 0.0, 0.0, 0.0, 0.0]}, {"name": "EPP3401", "dept": "서유럽팀", "leadTime": 159.4285714285714, "count": 7.0, "price": 0.0, "dist": [0.0, 0.0, 28.6, 0.0, 0.0, 0.0, 71.4, 0.0]}, {"name": "EPP3411", "dept": "서유럽팀", "leadTime": 70.0, "count": 2.0, "price": 4187000.0, "dist": [0.0, 0.0, 100.0, 0.0, 0.0, 0.0, 0.0, 0.0]}, {"name": "EPP3434", "dept": "서유럽팀", "leadTime": 79.25, "count": 8.0, "price": 0.0, "dist": [0.0, 0.0, 100.0, 0.0, 0.0, 0.0, 0.0, 0.0]}, {"name": "EPP3441", "dept": "서유럽팀", "leadTime": 59.81818181818182, "count": 11.0, "price": 5076000.0, "dist": [0.0, 72.7, 0.0, 27.3, 0.0, 0.0, 0.0, 0.0]}, {"name": "EPP3599", "dept": "서유럽팀", "leadTime": 74.66666666666667, "count": 24.0, "price": 2152500.0, "dist": [16.7, 50.0, 8.3, 8.3, 8.3, 0.0, 0.0, 8.3]}, {"name": "EPP3600", "dept": "서유럽팀", "leadTime": 71.0, "count": 2.0, "price": 5359630.0, "dist": [0.0, 0.0, 100.0, 0.0, 0.0, 0.0, 0.0, 0.0]}, {"name": "EPP3602", "dept": "서유럽팀", "leadTime": 128.0, "count": 6.0, "price": 4260000.0, "dist": [33.3, 0.0, 33.3, 0.0, 0.0, 0.0, 0.0, 33.3]}, {"name": "EPP3605", "dept": "서유럽팀", "leadTime": 133.0, "count": 2.0, "price": 0.0, "dist": [0.0, 0.0, 0.0, 0.0, 100.0, 0.0, 0.0, 0.0]}, {"name": "EPP3664", "dept": "서유럽팀", "leadTime": 142.0, "count": 7.0, "price": 3860800.0, "dist": [28.6, 0.0, 28.6, 0.0, 0.0, 0.0, 0.0, 42.9]}, {"name": "EPP3752", "dept": "서유럽팀", "leadTime": 87.0, "count": 5.0, "price": 0.0, "dist": [20.0, 0.0, 0.0, 80.0, 0.0, 0.0, 0.0, 0.0]}, {"name": "EPP3766", "dept": "서유럽팀", "leadTime": 137.8333333333333, "count": 6.0, "price": 3012420.0, "dist": [0.0, 0.0, 16.7, 0.0, 0.0, 83.3, 0.0, 0.0]}, {"name": "EPP3767", "dept": "서유럽팀", "leadTime": 70.28571428571429, "count": 14.0, "price": 1897090.909090909, "dist": [28.6, 0.0, 57.1, 0.0, 14.3, 0.0, 0.0, 0.0]}, {"name": "EPP3778", "dept": "서유럽팀", "leadTime": 137.0, "count": 1.0, "price": 0.0, "dist": [0.0, 0.0, 0.0, 0.0, 100.0, 0.0, 0.0, 0.0]}, {"name": "EPP3790", "dept": "서유럽팀", "leadTime": 217.3333333333333, "count": 6.0, "price": 3490000.0, "dist": [0.0, 0.0, 0.0, 33.3, 0.0, 0.0, 0.0, 66.7]}, {"name": "EPP3823", "dept": "서유럽팀", "leadTime": 187.6666666666667, "count": 18.0, "price": 2597000.0, "dist": [0.0, 0.0, 16.7, 0.0, 33.3, 5.6, 0.0, 44.4]}, {"name": "EPP3827", "dept": "서유럽팀", "leadTime": 145.0, "count": 4.0, "price": 3370000.0, "dist": [0.0, 0.0, 0.0, 0.0, 50.0, 50.0, 0.0, 0.0]}, {"name": "EPP3829", "dept": "서유럽팀", "leadTime": 136.0, "count": 4.0, "price": 0.0, "dist": [0.0, 0.0, 0.0, 0.0, 100.0, 0.0, 0.0, 0.0]}, {"name": "EPP3848", "dept": "서유럽팀", "leadTime": 15.0, "count": 2.0, "price": 2811317.0, "dist": [100.0, 0.0, 0.0, 0.0, 0.0, 0.0, 0.0, 0.0]}, {"name": "EPP385", "dept": "서유럽팀", "leadTime": 73.0, "count": 4.0, "price": 7438000.0, "dist": [0.0, 50.0, 25.0, 25.0, 0.0, 0.0, 0.0, 0.0]}, {"name": "EPP3880", "dept": "서유럽팀", "leadTime": 67.0, "count": 1.0, "price": 4267000.0, "dist": [0.0, 0.0, 100.0, 0.0, 0.0, 0.0, 0.0, 0.0]}, {"name": "EPP3921", "dept": "프리미엄팀", "leadTime": 17.0, "count": 1.0, "price": 0.0, "dist": [100.0, 0.0, 0.0, 0.0, 0.0, 0.0, 0.0, 0.0]}, {"name": "EPP4057", "dept": "동유럽팀", "leadTime": 30.75, "count": 4.0, "price": 0.0, "dist": [75.0, 25.0, 0.0, 0.0, 0.0, 0.0, 0.0, 0.0]}, {"name": "EPP4067", "dept": "동유럽팀", "leadTime": 63.0, "count": 5.0, "price": 3476000.0, "dist": [40.0, 0.0, 60.0, 0.0, 0.0, 0.0, 0.0, 0.0]}, {"name": "EPP4190", "dept": "동유럽팀", "leadTime": 20.0, "count": 2.0, "price": 2986000.0, "dist": [100.0, 0.0, 0.0, 0.0, 0.0, 0.0, 0.0, 0.0]}, {"name": "EPP4224", "dept": "동유럽팀", "leadTime": 31.5, "count": 6.0, "price": 3512400.0, "dist": [83.3, 16.7, 0.0, 0.0, 0.0, 0.0, 0.0, 0.0]}, {"name": "EPP4227", "dept": "동유럽팀", "leadTime": 118.5, "count": 8.0, "price": 0.0, "dist": [0.0, 0.0, 0.0, 50.0, 50.0, 0.0, 0.0, 0.0]}, {"name": "EPP4270", "dept": "동유럽팀", "leadTime": 67.4, "count": 5.0, "price": 0.0, "dist": [40.0, 0.0, 40.0, 20.0, 0.0, 0.0, 0.0, 0.0]}, {"name": "EPP4287", "dept": "동유럽팀", "leadTime": 9.0, "count": 2.0, "price": 0.0, "dist": [100.0, 0.0, 0.0, 0.0, 0.0, 0.0, 0.0, 0.0]}, {"name": "EPP4338", "dept": "동유럽팀", "leadTime": 100.5333333333333, "count": 15.0, "price": 2346666.666666667, "dist": [13.3, 33.3, 0.0, 26.7, 0.0, 0.0, 26.7, 0.0]}, {"name": "EPP4350", "dept": "동유럽팀", "leadTime": 135.6666666666667, "count": 6.0, "price": 2626666.666666667, "dist": [0.0, 33.3, 0.0, 0.0, 0.0, 0.0, 66.7, 0.0]}, {"name": "EPP4390", "dept": "동유럽팀", "leadTime": 95.45454545454545, "count": 11.0, "price": 3841666.666666667, "dist": [0.0, 0.0, 36.4, 45.5, 18.2, 0.0, 0.0, 0.0]}, {"name": "EPP4470", "dept": "동유럽팀", "leadTime": 29.0, "count": 2.0, "price": 0.0, "dist": [100.0, 0.0, 0.0, 0.0, 0.0, 0.0, 0.0, 0.0]}, {"name": "EPP4534", "dept": "프리미엄팀", "leadTime": 89.0, "count": 2.0, "price": 8290000.0, "dist": [0.0, 0.0, 100.0, 0.0, 0.0, 0.0, 0.0, 0.0]}, {"name": "EPP4557", "dept": "동유럽팀", "leadTime": 67.875, "count": 16.0, "price": 3595449.4, "dist": [62.5, 0.0, 0.0, 25.0, 0.0, 0.0, 12.5, 0.0]}, {"name": "EPP4562", "dept": "동유럽팀", "leadTime": 109.0, "count": 2.0, "price": 3007000.0, "dist": [0.0, 0.0, 0.0, 100.0, 0.0, 0.0, 0.0, 0.0]}, {"name": "EPP4568", "dept": "동유럽팀", "leadTime": 60.0, "count": 4.0, "price": 2980000.0, "dist": [0.0, 50.0, 50.0, 0.0, 0.0, 0.0, 0.0, 0.0]}, {"name": "EPP4580", "dept": "동유럽팀", "leadTime": 19.0, "count": 2.0, "price": 2890000.0, "dist": [100.0, 0.0, 0.0, 0.0, 0.0, 0.0, 0.0, 0.0]}, {"name": "EPP4640", "dept": "동유럽팀", "leadTime": 111.0, "count": 2.0, "price": 0.0, "dist": [0.0, 0.0, 0.0, 100.0, 0.0, 0.0, 0.0, 0.0]}, {"name": "EPP4648", "dept": "동유럽팀", "leadTime": 31.0, "count": 2.0, "price": 0.0, "dist": [0.0, 100.0, 0.0, 0.0, 0.0, 0.0, 0.0, 0.0]}, {"name": "EPP471", "dept": "동유럽팀", "leadTime": 130.0, "count": 2.0, "price": 0.0, "dist": [0.0, 0.0, 0.0, 0.0, 100.0, 0.0, 0.0, 0.0]}, {"name": "EPP4735", "dept": "동유럽팀", "leadTime": 47.0, "count": 2.0, "price": 0.0, "dist": [0.0, 100.0, 0.0, 0.0, 0.0, 0.0, 0.0, 0.0]}, {"name": "EPP4779", "dept": "동유럽팀", "leadTime": 80.0, "count": 4.0, "price": 3109000.0, "dist": [0.0, 0.0, 100.0, 0.0, 0.0, 0.0, 0.0, 0.0]}, {"name": "EPP4933", "dept": "동유럽팀", "leadTime": 29.0, "count": 2.0, "price": 0.0, "dist": [100.0, 0.0, 0.0, 0.0, 0.0, 0.0, 0.0, 0.0]}, {"name": "EPP500", "dept": "스페인/북유럽팀", "leadTime": 60.2, "count": 5.0, "price": 2680000.0, "dist": [60.0, 0.0, 0.0, 40.0, 0.0, 0.0, 0.0, 0.0]}, {"name": "EPP5014", "dept": "스페인/북유럽팀", "leadTime": 134.0, "count": 2.0, "price": 2250000.0, "dist": [0.0, 0.0, 0.0, 0.0, 100.0, 0.0, 0.0, 0.0]}, {"name": "EPP5070", "dept": "스페인/북유럽팀", "leadTime": 49.0, "count": 2.0, "price": 3236270.0, "dist": [0.0, 100.0, 0.0, 0.0, 0.0, 0.0, 0.0, 0.0]}, {"name": "EPP5072", "dept": "스페인/북유럽팀", "leadTime": 168.0, "count": 2.0, "price": 0.0, "dist": [0.0, 0.0, 0.0, 0.0, 0.0, 100.0, 0.0, 0.0]}, {"name": "EPP511", "dept": "스페인/북유럽팀", "leadTime": 113.5, "count": 8.0, "price": 1673333.333333333, "dist": [0.0, 0.0, 0.0, 75.0, 25.0, 0.0, 0.0, 0.0]}, {"name": "EPP525", "dept": "스페인/북유럽팀", "leadTime": 118.0, "count": 2.0, "price": 0.0, "dist": [0.0, 0.0, 0.0, 100.0, 0.0, 0.0, 0.0, 0.0]}, {"name": "EPP5445", "dept": "스페인/북유럽팀", "leadTime": 64.0, "count": 1.0, "price": 0.0, "dist": [0.0, 0.0, 100.0, 0.0, 0.0, 0.0, 0.0, 0.0]}, {"name": "EPP545", "dept": "스페인/북유럽팀", "leadTime": 173.6666666666667, "count": 18.0, "price": 2016312.5, "dist": [0.0, 0.0, 44.4, 0.0, 0.0, 0.0, 0.0, 55.6]}, {"name": "EPP553", "dept": "스페인/북유럽팀", "leadTime": 64.78947368421052, "count": 19.0, "price": 1918509.230769231, "dist": [10.5, 36.8, 42.1, 0.0, 10.5, 0.0, 0.0, 0.0]}, {"name": "EPP554", "dept": "스페인/북유럽팀", "leadTime": 111.4, "count": 5.0, "price": 2430000.0, "dist": [0.0, 0.0, 40.0, 0.0, 60.0, 0.0, 0.0, 0.0]}, {"name": "EPP5578", "dept": "스페인/북유럽팀", "leadTime": 135.4615384615385, "count": 13.0, "price": 3001300.0, "dist": [0.0, 15.4, 15.4, 15.4, 23.1, 0.0, 0.0, 30.8]}, {"name": "EPP5604", "dept": "프리미엄팀", "leadTime": 72.0, "count": 2.0, "price": 0.0, "dist": [0.0, 0.0, 100.0, 0.0, 0.0, 0.0, 0.0, 0.0]}, {"name": "EPP5648", "dept": "스페인/북유럽팀", "leadTime": 190.1666666666667, "count": 6.0, "price": 1752000.0, "dist": [0.0, 0.0, 16.7, 0.0, 16.7, 0.0, 0.0, 66.7]}, {"name": "EPP5744", "dept": "지중해/인도/아프리카팀", "leadTime": 106.0, "count": 2.0, "price": 0.0, "dist": [0.0, 0.0, 0.0, 100.0, 0.0, 0.0, 0.0, 0.0]}, {"name": "EPP5746", "dept": "지중해/인도/아프리카팀", "leadTime": 56.66666666666666, "count": 3.0, "price": 3520000.0, "dist": [0.0, 100.0, 0.0, 0.0, 0.0, 0.0, 0.0, 0.0]}, {"name": "FPP125", "dept": "지중해/인도/아프리카팀", "leadTime": 192.0, "count": 2.0, "price": 0.0, "dist": [0.0, 0.0, 0.0, 0.0, 0.0, 0.0, 100.0, 0.0]}, {"name": "FPP153", "dept": "지중해/인도/아프리카팀", "leadTime": 37.0, "count": 1.0, "price": 6090000.0, "dist": [0.0, 100.0, 0.0, 0.0, 0.0, 0.0, 0.0, 0.0]}, {"name": "IPF102", "dept": "남태평양팀", "leadTime": 25.0, "count": 4.0, "price": 729000.0, "dist": [100.0, 0.0, 0.0, 0.0, 0.0, 0.0, 0.0, 0.0]}, {"name": "IPF104", "dept": "남태평양팀", "leadTime": 23.0, "count": 2.0, "price": 649000.0, "dist": [100.0, 0.0, 0.0, 0.0, 0.0, 0.0, 0.0, 0.0]}, {"name": "IPF109", "dept": "남태평양팀", "leadTime": 36.0, "count": 6.0, "price": 1403166.666666667, "dist": [0.0, 100.0, 0.0, 0.0, 0.0, 0.0, 0.0, 0.0]}, {"name": "IPF263", "dept": "남태평양팀", "leadTime": 37.0, "count": 5.0, "price": 853000.0, "dist": [0.0, 100.0, 0.0, 0.0, 0.0, 0.0, 0.0, 0.0]}, {"name": "IPF360", "dept": "남태평양팀", "leadTime": 29.25, "count": 12.0, "price": 1237555.555555556, "dist": [50.0, 50.0, 0.0, 0.0, 0.0, 0.0, 0.0, 0.0]}, {"name": "IPF440", "dept": "남태평양팀", "leadTime": 12.5, "count": 8.0, "price": 710644.0, "dist": [100.0, 0.0, 0.0, 0.0, 0.0, 0.0, 0.0, 0.0]}, {"name": "IPF560", "dept": "남태평양팀", "leadTime": 26.0, "count": 4.0, "price": 0.0, "dist": [100.0, 0.0, 0.0, 0.0, 0.0, 0.0, 0.0, 0.0]}, {"name": "IPF566", "dept": "남태평양팀", "leadTime": 99.0, "count": 4.0, "price": 2232000.0, "dist": [0.0, 0.0, 0.0, 100.0, 0.0, 0.0, 0.0, 0.0]}, {"name": "IPF568", "dept": "남태평양팀", "leadTime": 30.0, "count": 4.0, "price": 950000.0, "dist": [100.0, 0.0, 0.0, 0.0, 0.0, 0.0, 0.0, 0.0]}, {"name": "IPG105", "dept": "남태평양팀", "leadTime": 182.0, "count": 2.0, "price": 2400000.0, "dist": [0.0, 0.0, 0.0, 0.0, 0.0, 0.0, 100.0, 0.0]}, {"name": "IPP560", "dept": "부산지점", "leadTime": 54.5, "count": 4.0, "price": 909724.3333333334, "dist": [0.0, 25.0, 75.0, 0.0, 0.0, 0.0, 0.0, 0.0]}, {"name": "IPP5602", "dept": "부산지점", "leadTime": 35.0, "count": 5.0, "price": 0.0, "dist": [0.0, 100.0, 0.0, 0.0, 0.0, 0.0, 0.0, 0.0]}, {"name": "IPP566", "dept": "부산지점", "leadTime": 74.0, "count": 2.0, "price": 814730.0, "dist": [0.0, 0.0, 100.0, 0.0, 0.0, 0.0, 0.0, 0.0]}, {"name": "JPC953", "dept": "부산지점", "leadTime": 44.125, "count": 8.0, "price": 202143.75, "dist": [0.0, 100.0, 0.0, 0.0, 0.0, 0.0, 0.0, 0.0]}, {"name": "JPP016", "dept": "일본팀", "leadTime": 57.9, "count": 10.0, "price": 1959000.0, "dist": [50.0, 20.0, 0.0, 20.0, 10.0, 0.0, 0.0, 0.0]}, {"name": "JPP0166", "dept": "일본팀", "leadTime": 51.66666666666666, "count": 6.0, "price": 1599000.0, "dist": [0.0, 100.0, 0.0, 0.0, 0.0, 0.0, 0.0, 0.0]}, {"name": "JPP018", "dept": "일본팀", "leadTime": 59.17307692307692, "count": 52.0, "price": 936985.4166666666, "dist": [42.3, 13.5, 28.8, 0.0, 15.4, 0.0, 0.0, 0.0]}, {"name": "JPP019", "dept": "일본팀", "leadTime": 62.95238095238095, "count": 21.0, "price": 1505476.470588235, "dist": [9.5, 42.9, 19.0, 28.6, 0.0, 0.0, 0.0, 0.0]}, {"name": "JPP020", "dept": "일본팀", "leadTime": 268.0, "count": 2.0, "price": 899000.0, "dist": [0.0, 0.0, 0.0, 0.0, 0.0, 0.0, 0.0, 100.0]}, {"name": "JPP023", "dept": "일본팀", "leadTime": 78.66666666666667, "count": 6.0, "price": 1399000.0, "dist": [0.0, 33.3, 16.7, 50.0, 0.0, 0.0, 0.0, 0.0]}, {"name": "JPP0808", "dept": "일본팀", "leadTime": 72.0, "count": 2.0, "price": 0.0, "dist": [0.0, 0.0, 100.0, 0.0, 0.0, 0.0, 0.0, 0.0]}, {"name": "JPP088", "dept": "일본팀", "leadTime": 50.34782608695652, "count": 23.0, "price": 1240811.619047619, "dist": [8.7, 65.2, 13.0, 13.0, 0.0, 0.0, 0.0, 0.0]}, {"name": "JPP398", "dept": "일본팀", "leadTime": 125.0, "count": 7.0, "price": 0.0, "dist": [0.0, 0.0, 0.0, 0.0, 100.0, 0.0, 0.0, 0.0]}, {"name": "JPP488", "dept": "일본팀", "leadTime": 19.0, "count": 4.0, "price": 0.0, "dist": [100.0, 0.0, 0.0, 0.0, 0.0, 0.0, 0.0, 0.0]}, {"name": "JPP4881", "dept": "일본팀", "leadTime": 121.0, "count": 2.0, "price": 0.0, "dist": [0.0, 0.0, 0.0, 0.0, 100.0, 0.0, 0.0, 0.0]}, {"name": "JPP565", "dept": "일본팀", "leadTime": 31.2, "count": 10.0, "price": 777000.0, "dist": [60.0, 40.0, 0.0, 0.0, 0.0, 0.0, 0.0, 0.0]}, {"name": "JPP649", "dept": "일본팀", "leadTime": 69.0, "count": 4.0, "price": 1049000.0, "dist": [50.0, 0.0, 0.0, 50.0, 0.0, 0.0, 0.0, 0.0]}, {"name": "JPP654", "dept": "일본팀", "leadTime": 18.33333333333333, "count": 3.0, "price": 0.0, "dist": [100.0, 0.0, 0.0, 0.0, 0.0, 0.0, 0.0, 0.0]}, {"name": "JPP6640", "dept": "일본팀", "leadTime": 24.0, "count": 13.0, "price": 99846.15384615384, "dist": [100.0, 0.0, 0.0, 0.0, 0.0, 0.0, 0.0, 0.0]}, {"name": "JPP6644", "dept": "일본팀", "leadTime": 62.16666666666666, "count": 12.0, "price": 669266.6666666666, "dist": [16.7, 0.0, 83.3, 0.0, 0.0, 0.0, 0.0, 0.0]}, {"name": "JPP6690", "dept": "일본팀", "leadTime": 68.95833333333333, "count": 24.0, "price": 806154.0, "dist": [37.5, 12.5, 16.7, 8.3, 25.0, 0.0, 0.0, 0.0]}, {"name": "JPP7000", "dept": "일본팀", "leadTime": 98.0, "count": 2.0, "price": 0.0, "dist": [0.0, 0.0, 0.0, 100.0, 0.0, 0.0, 0.0, 0.0]}, {"name": "JPP7005", "dept": "일본팀", "leadTime": 233.0, "count": 4.0, "price": 0.0, "dist": [0.0, 0.0, 0.0, 0.0, 0.0, 0.0, 0.0, 100.0]}, {"name": "JPP821", "dept": "부산지점", "leadTime": 30.0, "count": 2.0, "price": 793660.0, "dist": [100.0, 0.0, 0.0, 0.0, 0.0, 0.0, 0.0, 0.0]}, {"name": "JPP822", "dept": "부산지점", "leadTime": 49.0, "count": 2.0, "price": 0.0, "dist": [0.0, 100.0, 0.0, 0.0, 0.0, 0.0, 0.0, 0.0]}, {"name": "JPP823", "dept": "부산지점", "leadTime": 55.5, "count": 8.0, "price": 665000.0, "dist": [50.0, 0.0, 0.0, 50.0, 0.0, 0.0, 0.0, 0.0]}, {"name": "JPP842", "dept": "부산지점", "leadTime": 17.0, "count": 2.0, "price": 1229000.0, "dist": [100.0, 0.0, 0.0, 0.0, 0.0, 0.0, 0.0, 0.0]}, {"name": "JPP943", "dept": "부산지점", "leadTime": 71.0, "count": 6.0, "price": 0.0, "dist": [0.0, 0.0, 100.0, 0.0, 0.0, 0.0, 0.0, 0.0]}, {"name": "JPP953", "dept": "부산지점", "leadTime": 73.0, "count": 6.0, "price": 0.0, "dist": [0.0, 0.0, 100.0, 0.0, 0.0, 0.0, 0.0, 0.0]}, {"name": "JPP959", "dept": "부산지점", "leadTime": 19.0, "count": 1.0, "price": 148700.0, "dist": [100.0, 0.0, 0.0, 0.0, 0.0, 0.0, 0.0, 0.0]}, {"name": "JPPT501", "dept": "대구지점", "leadTime": 51.0, "count": 3.0, "price": 199000.0, "dist": [0.0, 100.0, 0.0, 0.0, 0.0, 0.0, 0.0, 0.0]}, {"name": "KFF201", "dept": "국내팀", "leadTime": 25.0, "count": 5.0, "price": 0.0, "dist": [100.0, 0.0, 0.0, 0.0, 0.0, 0.0, 0.0, 0.0]}, {"name": "KPI115", "dept": "국내팀", "leadTime": 12.0, "count": 2.0, "price": 0.0, "dist": [100.0, 0.0, 0.0, 0.0, 0.0, 0.0, 0.0, 0.0]}, {"name": "KPI116", "dept": "국내팀", "leadTime": 65.0, "count": 4.0, "price": 265000.0, "dist": [0.0, 0.0, 100.0, 0.0, 0.0, 0.0, 0.0, 0.0]}, {"name": "KPI400", "dept": "국내팀", "leadTime": 101.0, "count": 9.0, "price": 0.0, "dist": [0.0, 0.0, 0.0, 100.0, 0.0, 0.0, 0.0, 0.0]}, {"name": "KPI506", "dept": "국내팀", "leadTime": 30.0, "count": 12.0, "price": 449166.6666666667, "dist": [16.7, 83.3, 0.0, 0.0, 0.0, 0.0, 0.0, 0.0]}, {"name": "KPP137", "dept": "국내팀", "leadTime": 55.0, "count": 4.0, "price": 360000.0, "dist": [50.0, 0.0, 0.0, 50.0, 0.0, 0.0, 0.0, 0.0]}, {"name": "KPP323", "dept": "국내팀", "leadTime": 15.0, "count": 2.0, "price": 596000.0, "dist": [100.0, 0.0, 0.0, 0.0, 0.0, 0.0, 0.0, 0.0]}, {"name": "KPP418", "dept": "국내팀", "leadTime": 11.0, "count": 4.0, "price": 250000.0, "dist": [100.0, 0.0, 0.0, 0.0, 0.0, 0.0, 0.0, 0.0]}, {"name": "MPP115", "dept": "지중해/인도/아프리카팀", "leadTime": 45.0, "count": 2.0, "price": 0.0, "dist": [0.0, 100.0, 0.0, 0.0, 0.0, 0.0, 0.0, 0.0]}, {"name": "MPP900", "dept": "지중해/인도/아프리카팀", "leadTime": 90.83333333333333, "count": 12.0, "price": 2009000.0, "dist": [16.7, 16.7, 33.3, 16.7, 0.0, 0.0, 16.7, 0.0]}, {"name": "MPP947", "dept": "지중해/인도/아프리카팀", "leadTime": 65.53846153846153, "count": 13.0, "price": 1163500.0, "dist": [0.0, 38.5, 46.2, 15.4, 0.0, 0.0, 0.0, 0.0]}, {"name": "PPF281", "dept": "남태평양팀", "leadTime": 53.0, "count": 2.0, "price": 0.0, "dist": [0.0, 100.0, 0.0, 0.0, 0.0, 0.0, 0.0, 0.0]}, {"name": "PPP202", "dept": "남태평양팀", "leadTime": 47.0, "count": 3.0, "price": 2349000.0, "dist": [0.0, 100.0, 0.0, 0.0, 0.0, 0.0, 0.0, 0.0]}, {"name": "PPP204", "dept": "남태평양팀", "leadTime": 40.8, "count": 10.0, "price": 2199000.0, "dist": [40.0, 60.0, 0.0, 0.0, 0.0, 0.0, 0.0, 0.0]}, {"name": "PPP212", "dept": "남태평양팀", "leadTime": 22.61904761904762, "count": 21.0, "price": 1213666.666666667, "dist": [90.5, 9.5, 0.0, 0.0, 0.0, 0.0, 0.0, 0.0]}, {"name": "PPP257", "dept": "미주팀", "leadTime": 29.0, "count": 3.0, "price": 0.0, "dist": [100.0, 0.0, 0.0, 0.0, 0.0, 0.0, 0.0, 0.0]}, {"name": "PPP258", "dept": "남태평양팀", "leadTime": 141.0, "count": 2.0, "price": 0.0, "dist": [0.0, 0.0, 0.0, 0.0, 100.0, 0.0, 0.0, 0.0]}, {"name": "PPP282", "dept": "남태평양팀", "leadTime": 35.0, "count": 3.0, "price": 1649000.0, "dist": [0.0, 100.0, 0.0, 0.0, 0.0, 0.0, 0.0, 0.0]}, {"name": "PPP330", "dept": "남태평양팀", "leadTime": 100.0, "count": 4.0, "price": 3304500.0, "dist": [0.0, 50.0, 0.0, 0.0, 50.0, 0.0, 0.0, 0.0]}, {"name": "PPP809", "dept": "남태평양팀", "leadTime": 104.3333333333333, "count": 6.0, "price": 3939000.0, "dist": [0.0, 0.0, 33.3, 33.3, 33.3, 0.0, 0.0, 0.0]}, {"name": "UPP207", "dept": "미주팀", "leadTime": 126.0, "count": 2.0, "price": 0.0, "dist": [0.0, 0.0, 0.0, 0.0, 100.0, 0.0, 0.0, 0.0]}, {"name": "UPP3824", "dept": "미주팀", "leadTime": 82.0, "count": 4.0, "price": 2405000.0, "dist": [0.0, 0.0, 100.0, 0.0, 0.0, 0.0, 0.0, 0.0]}, {"name": "UPP3982", "dept": "미주팀", "leadTime": 90.6, "count": 5.0, "price": 3690000.0, "dist": [0.0, 0.0, 40.0, 60.0, 0.0, 0.0, 0.0, 0.0]}, {"name": "UPP3986", "dept": "미주팀", "leadTime": 125.0, "count": 1.0, "price": 0.0, "dist": [0.0, 0.0, 0.0, 0.0, 100.0, 0.0, 0.0, 0.0]}, {"name": "UPP4511", "dept": "미주팀", "leadTime": 96.0, "count": 1.0, "price": 0.0, "dist": [0.0, 0.0, 0.0, 100.0, 0.0, 0.0, 0.0, 0.0]}, {"name": "UPP452", "dept": "미주팀", "leadTime": 76.5, "count": 16.0, "price": 3006466.666666667, "dist": [25.0, 12.5, 0.0, 62.5, 0.0, 0.0, 0.0, 0.0]}, {"name": "UPP4612", "dept": "미주팀", "leadTime": 63.0, "count": 2.0, "price": 0.0, "dist": [0.0, 0.0, 100.0, 0.0, 0.0, 0.0, 0.0, 0.0]}, {"name": "UPP467", "dept": "미주팀", "leadTime": 36.0, "count": 2.0, "price": 0.0, "dist": [0.0, 100.0, 0.0, 0.0, 0.0, 0.0, 0.0, 0.0]}, {"name": "UPP601", "dept": "미주팀", "leadTime": 41.0, "count": 6.0, "price": 20000.0, "dist": [0.0, 100.0, 0.0, 0.0, 0.0, 0.0, 0.0, 0.0]}, {"name": "UPP621", "dept": "미주팀", "leadTime": 206.0, "count": 2.0, "price": 21890000.0, "dist": [0.0, 0.0, 0.0, 0.0, 0.0, 0.0, 100.0, 0.0]}, {"name": "UPP672", "dept": "미주팀", "leadTime": 95.0, "count": 1.0, "price": 10990000.0, "dist": [0.0, 0.0, 0.0, 100.0, 0.0, 0.0, 0.0, 0.0]}, {"name": "ZPP2077", "dept": "중국팀", "leadTime": 89.33333333333333, "count": 3.0, "price": 5390000.0, "dist": [0.0, 0.0, 66.7, 33.3, 0.0, 0.0, 0.0, 0.0]}], "price": [{"name": "100~200만 미만", "leadTime": 60.48339483394834, "count": 271.0, "price": 0.0, "dist": [27.3, 37.3, 8.9, 18.5, 4.8, 1.1, 0.7, 1.5]}, {"name": "200~300만 미만", "leadTime": 113.1165048543689, "count": 103.0, "price": 0.0, "dist": [26.2, 6.8, 17.5, 7.8, 9.7, 0.0, 22.3, 9.7]}, {"name": "300만~", "leadTime": 80.54347826086956, "count": 138.0, "price": 0.0, "dist": [26.1, 22.5, 15.2, 18.1, 10.1, 1.4, 1.4, 5.1]}, {"name": "50~100만 미만", "leadTime": 49.09686609686609, "count": 351.0, "price": 0.0, "dist": [51.0, 18.5, 13.7, 9.1, 4.6, 2.6, 0.0, 0.6]}, {"name": "50만 미만", "leadTime": 51.58561643835616, "count": 292.0, "price": 0.0, "dist": [47.9, 15.4, 17.5, 10.3, 8.9, 0.0, 0.0, 0.0]}]}