{"kpi": {"leadTime": 64.45664739884393, "count": 1730.0, "price": 1697909.371035308, "dist": [27.2, 32.1, 20.8, 7.8, 5.1, 3.8, 1.4, 1.9]}, "dept": [{"name": "국내팀", "leadTime": 49.59375, "count": 32.0, "price": 431733.3333333333, "dist": [21.9, 75.0, 3.1, 0.0, 0.0, 0.0, 0.0, 0.0]}, {"name": "남태평양팀", "leadTime": 62.77777777777778, "count": 18.0, "price": 2222305.0, "dist": [38.9, 22.2, 22.2, 0.0, 16.7, 0.0, 0.0, 0.0]}, {"name": "대구지점", "leadTime": 37.9, "count": 30.0, "price": 839101.3333333334, "dist": [13.3, 86.7, 0.0, 0.0, 0.0, 0.0, 0.0, 0.0]}, {"name": "동남아1팀", "leadTime": 63.01734104046243, "count": 173.0, "price": 855324.6473988439, "dist": [25.4, 42.2, 11.6, 6.4, 0.0, 14.5, 0.0, 0.0]}, {"name": "동남아2팀", "leadTime": 52.61320754716981, "count": 106.0, "price": 846135.0943396227, "dist": [28.3, 24.5, 40.6, 6.6, 0.0, 0.0, 0.0, 0.0]}, {"name": "동유럽팀", "leadTime": 76.55191256830601, "count": 183.0, "price": 2847299.696132597, "dist": [21.3, 31.7, 16.4, 5.5, 9.3, 7.1, 8.7, 0.0]}, {"name": "미주팀", "leadTime": 82.3030303030303, "count": 33.0, "price": 4243272.727272728, "dist": [18.2, 18.2, 30.3, 15.2, 12.1, 0.0, 0.0, 6.1]}, {"name": "부산지점", "leadTime": 46.38655462184874, "count": 119.0, "price": 937216.2393162394, "dist": [47.1, 24.4, 16.8, 11.8, 0.0, 0.0, 0.0, 0.0]}, {"name": "서유럽팀", "leadTime": 105.013422818792, "count": 149.0, "price": 3958665.915492958, "dist": [22.8, 16.8, 24.2, 4.0, 14.8, 1.3, 1.3, 14.8]}, {"name": "스페인/북유럽팀", "leadTime": 76.7936507936508, "count": 63.0, "price": 3671707.936507937, "dist": [7.9, 38.1, 28.6, 19.0, 0.0, 3.2, 0.0, 3.2]}, {"name": "일본팀", "leadTime": 48.24183006535948, "count": 306.0, "price": 1240866.897689769, "dist": [34.6, 43.1, 9.8, 5.2, 2.9, 4.2, 0.0, 0.0]}, {"name": "중국팀", "leadTime": 64.72246696035242, "count": 227.0, "price": 912286.4705882353, "dist": [20.3, 23.8, 33.9, 10.6, 8.8, 2.6, 0.0, 0.0]}, {"name": "지중해/인도/아프리카팀", "leadTime": 85.31147540983606, "count": 61.0, "price": 2405045.454545455, "dist": [14.8, 23.0, 29.5, 6.6, 16.4, 3.3, 1.6, 4.9]}, {"name": "크루즈/테마팀", "leadTime": 224.3333333333333, "count": 6.0, "price": 6823333.333333333, "dist": [0.0, 0.0, 0.0, 33.3, 0.0, 0.0, 0.0, 66.7]}, {"name": "태국파트", "leadTime": 56.72413793103448, "count": 145.0, "price": 603741.8571428572, "dist": [38.6, 22.8, 21.4, 12.4, 0.0, 1.4, 3.4, 0.0]}, {"name": "프리미엄팀", "leadTime": 48.75, "count": 8.0, "price": 10865000.0, "dist": [0.0, 100.0, 0.0, 0.0, 0.0, 0.0, 0.0, 0.0]}, {"name": "필리핀/말레이시아파트", "leadTime": 53.91549295774648, "count": 71.0, "price": 1036605.633802817, "dist": [29.6, 28.2, 29.6, 8.5, 4.2, 0.0, 0.0, 0.0]}], "prod": [{"name": "AGP5380", "dept": "동남아1팀", "leadTime": 26.0, "count": 2.0, "price": 726530.0, "dist": [100.0, 0.0, 0.0, 0.0, 0.0, 0.0, 0.0, 0.0]}, {"name": "APF123", "dept": "태국파트", "leadTime": 39.0, "count": 4.0, "price": 869000.0, "dist": [0.0, 100.0, 0.0, 0.0, 0.0, 0.0, 0.0, 0.0]}, {"name": "APF8427", "dept": "태국파트", "leadTime": 65.0, "count": 2.0, "price": 649000.0, "dist": [0.0, 0.0, 100.0, 0.0, 0.0, 0.0, 0.0, 0.0]}, {"name": "APF8999", "dept": "동남아1팀", "leadTime": 30.0, "count": 4.0, "price": 949000.0, "dist": [100.0, 0.0, 0.0, 0.0, 0.0, 0.0, 0.0, 0.0]}, {"name": "APF975", "dept": "동남아2팀", "leadTime": 28.0, "count": 4.0, "price": 1449000.0, "dist": [100.0, 0.0, 0.0, 0.0, 0.0, 0.0, 0.0, 0.0]}, {"name": "APP0075", "dept": "필리핀/말레이시아파트", "leadTime": 101.0, "count": 4.0, "price": 1829000.0, "dist": [0.0, 0.0, 0.0, 100.0, 0.0, 0.0, 0.0, 0.0]}, {"name": "APP0079", "dept": "필리핀/말레이시아파트", "leadTime": 26.0, "count": 2.0, "price": 1299000.0, "dist": [100.0, 0.0, 0.0, 0.0, 0.0, 0.0, 0.0, 0.0]}, {"name": "APP0237", "dept": "동남아1팀", "leadTime": 47.71428571428572, "count": 14.0, "price": 746833.7142857143, "dist": [0.0, 57.1, 42.9, 0.0, 0.0, 0.0, 0.0, 0.0]}, {"name": "APP0671", "dept": "필리핀/말레이시아파트", "leadTime": 112.0, "count": 2.0, "price": 969000.0, "dist": [0.0, 0.0, 0.0, 100.0, 0.0, 0.0, 0.0, 0.0]}, {"name": "APP0748", "dept": "부산지점", "leadTime": 96.0, "count": 4.0, "price": 1659000.0, "dist": [0.0, 0.0, 0.0, 100.0, 0.0, 0.0, 0.0, 0.0]}, {"name": "APP0798", "dept": "부산지점", "leadTime": 19.0, "count": 2.0, "price": 766230.0, "dist": [100.0, 0.0, 0.0, 0.0, 0.0, 0.0, 0.0, 0.0]}, {"name": "APP0889", "dept": "필리핀/말레이시아파트", "leadTime": 45.5625, "count": 16.0, "price": 999000.0, "dist": [37.5, 0.0, 62.5, 0.0, 0.0, 0.0, 0.0, 0.0]}, {"name": "APP1100", "dept": "동남아2팀", "leadTime": 34.0, "count": 5.0, "price": 639000.0, "dist": [80.0, 0.0, 20.0, 0.0, 0.0, 0.0, 0.0, 0.0]}, {"name": "APP1141", "dept": "동남아2팀", "leadTime": 50.0, "count": 3.0, "price": 1249000.0, "dist": [0.0, 100.0, 0.0, 0.0, 0.0, 0.0, 0.0, 0.0]}, {"name": "APP1200", "dept": "동남아2팀", "leadTime": 44.5, "count": 8.0, "price": 781000.0, "dist": [50.0, 0.0, 50.0, 0.0, 0.0, 0.0, 0.0, 0.0]}, {"name": "APP1291", "dept": "동남아1팀", "leadTime": 57.0, "count": 3.0, "price": 649000.0, "dist": [0.0, 100.0, 0.0, 0.0, 0.0, 0.0, 0.0, 0.0]}, {"name": "APP130", "dept": "동남아2팀", "leadTime": 59.61538461538461, "count": 26.0, "price": 759000.0, "dist": [11.5, 50.0, 23.1, 15.4, 0.0, 0.0, 0.0, 0.0]}, {"name": "APP1314", "dept": "동남아1팀", "leadTime": 118.0, "count": 3.0, "price": 499000.0, "dist": [0.0, 0.0, 0.0, 100.0, 0.0, 0.0, 0.0, 0.0]}, {"name": "APP136", "dept": "동남아2팀", "leadTime": 80.0, "count": 5.0, "price": 949000.0, "dist": [0.0, 0.0, 100.0, 0.0, 0.0, 0.0, 0.0, 0.0]}, {"name": "APP1399", "dept": "동남아2팀", "leadTime": 24.0, "count": 4.0, "price": 919080.0, "dist": [100.0, 0.0, 0.0, 0.0, 0.0, 0.0, 0.0, 0.0]}, {"name": "APP1982", "dept": "동남아1팀", "leadTime": 47.45454545454545, "count": 11.0, "price": 981272.7272727273, "dist": [0.0, 100.0, 0.0, 0.0, 0.0, 0.0, 0.0, 0.0]}, {"name": "APP2468", "dept": "필리핀/말레이시아파트", "leadTime": 60.0, "count": 6.0, "price": 2165666.666666667, "dist": [0.0, 33.3, 66.7, 0.0, 0.0, 0.0, 0.0, 0.0]}, {"name": "APP2528", "dept": "동남아1팀", "leadTime": 119.0, "count": 2.0, "price": 749000.0, "dist": [0.0, 0.0, 0.0, 100.0, 0.0, 0.0, 0.0, 0.0]}, {"name": "APP2625", "dept": "동남아1팀", "leadTime": 25.0, "count": 3.0, "price": 599000.0, "dist": [100.0, 0.0, 0.0, 0.0, 0.0, 0.0, 0.0, 0.0]}, {"name": "APP3054", "dept": "동남아1팀", "leadTime": 73.0, "count": 3.0, "price": 699000.0, "dist": [0.0, 0.0, 100.0, 0.0, 0.0, 0.0, 0.0, 0.0]}, {"name": "APP3370", "dept": "필리핀/말레이시아파트", "leadTime": 26.71428571428572, "count": 7.0, "price": 877571.4285714285, "dist": [57.1, 42.9, 0.0, 0.0, 0.0, 0.0, 0.0, 0.0]}, {"name": "APP3375", "dept": "동남아1팀", "leadTime": 60.0, "count": 12.0, "price": 1149000.0, "dist": [0.0, 66.7, 0.0, 33.3, 0.0, 0.0, 0.0, 0.0]}, {"name": "APP3985", "dept": "태국파트", "leadTime": 54.75454545454546, "count": 110.0, "price": 521704.7619047619, "dist": [34.5, 26.4, 22.7, 16.4, 0.0, 0.0, 0.0, 0.0]}, {"name": "APP3991", "dept": "태국파트", "leadTime": 58.25, "count": 8.0, "price": 949000.0, "dist": [75.0, 0.0, 0.0, 0.0, 0.0, 25.0, 0.0, 0.0]}, {"name": "APP4206", "dept": "부산지점", "leadTime": 52.0, "count": 4.0, "price": 842930.0, "dist": [0.0, 100.0, 0.0, 0.0, 0.0, 0.0, 0.0, 0.0]}, {"name": "APP4335", "dept": "필리핀/말레이시아파트", "leadTime": 66.5, "count": 4.0, "price": 649000.0, "dist": [0.0, 50.0, 50.0, 0.0, 0.0, 0.0, 0.0, 0.0]}, {"name": "APP4412", "dept": "필리핀/말레이시아파트", "leadTime": 57.0, "count": 6.0, "price": 789000.0, "dist": [0.0, 100.0, 0.0, 0.0, 0.0, 0.0, 0.0, 0.0]}, {"name": "APP4661", "dept": "필리핀/말레이시아파트", "leadTime": 20.0, "count": 4.0, "price": 849000.0, "dist": [100.0, 0.0, 0.0, 0.0, 0.0, 0.0, 0.0, 0.0]}, {"name": "APP4920", "dept": "필리핀/말레이시아파트", "leadTime": 9.0, "count": 3.0, "price": 529000.0, "dist": [100.0, 0.0, 0.0, 0.0, 0.0, 0.0, 0.0, 0.0]}, {"name": "APP5159", "dept": "태국파트", "leadTime": 65.0, "count": 2.0, "price": 489000.0, "dist": [0.0, 0.0, 100.0, 0.0, 0.0, 0.0, 0.0, 0.0]}, {"name": "APP5228", "dept": "동남아1팀", "leadTime": 31.0, "count": 24.0, "price": 1033934.0, "dist": [50.0, 50.0, 0.0, 0.0, 0.0, 0.0, 0.0, 0.0]}, {"name": "APP5250", "dept": "태국파트", "leadTime": 27.0, "count": 4.0, "price": 634000.0, "dist": [100.0, 0.0, 0.0, 0.0, 0.0, 0.0, 0.0, 0.0]}, {"name": "APP5259", "dept": "동남아1팀", "leadTime": 58.0, "count": 6.0, "price": 399000.0, "dist": [0.0, 100.0, 0.0, 0.0, 0.0, 0.0, 0.0, 0.0]}, {"name": "APP5359", "dept": "동남아1팀", "leadTime": 48.6875, "count": 16.0, "price": 647450.0, "dist": [25.0, 37.5, 37.5, 0.0, 0.0, 0.0, 0.0, 0.0]}, {"name": "APP5368", "dept": "동남아1팀", "leadTime": 18.0, "count": 2.0, "price": 599000.0, "dist": [100.0, 0.0, 0.0, 0.0, 0.0, 0.0, 0.0, 0.0]}, {"name": "APP5400", "dept": "동남아2팀", "leadTime": 61.64285714285715, "count": 28.0, "price": 940071.4285714285, "dist": [10.7, 7.1, 71.4, 10.7, 0.0, 0.0, 0.0, 0.0]}, {"name": "APP5440", "dept": "동남아2팀", "leadTime": 36.2, "count": 10.0, "price": 599000.0, "dist": [60.0, 40.0, 0.0, 0.0, 0.0, 0.0, 0.0, 0.0]}, {"name": "APP5575", "dept": "동남아1팀", "leadTime": 36.0, "count": 2.0, "price": 949000.0, "dist": [0.0, 100.0, 0.0, 0.0, 0.0, 0.0, 0.0, 0.0]}, {"name": "APP5918", "dept": "동남아1팀", "leadTime": 30.0, "count": 4.0, "price": 699000.0, "dist": [100.0, 0.0, 0.0, 0.0, 0.0, 0.0, 0.0, 0.0]}, {"name": "APP5990", "dept": "동남아2팀", "leadTime": 50.38461538461539, "count": 13.0, "price": 787461.5384615385, "dist": [15.4, 30.8, 53.8, 0.0, 0.0, 0.0, 0.0, 0.0]}, {"name": "APP5999", "dept": "필리핀/말레이시아파트", "leadTime": 45.0, "count": 5.0, "price": 893000.0, "dist": [40.0, 60.0, 0.0, 0.0, 0.0, 0.0, 0.0, 0.0]}, {"name": "APP6042", "dept": "동남아1팀", "leadTime": 169.0, "count": 6.0, "price": 1499000.0, "dist": [0.0, 0.0, 0.0, 0.0, 0.0, 100.0, 0.0, 0.0]}, {"name": "APP6651", "dept": "동남아1팀", "leadTime": 42.0, "count": 9.0, "price": 948791.1111111111, "dist": [0.0, 100.0, 0.0, 0.0, 0.0, 0.0, 0.0, 0.0]}, {"name": "APP6675", "dept": "동남아1팀", "leadTime": 123.5, "count": 4.0, "price": 999000.0, "dist": [25.0, 0.0, 0.0, 0.0, 0.0, 75.0, 0.0, 0.0]}, {"name": "APP6902", "dept": "필리핀/말레이시아파트", "leadTime": 121.0, "count": 3.0, "price": 899000.0, "dist": [0.0, 0.0, 0.0, 0.0, 100.0, 0.0, 0.0, 0.0]}, {"name": "APP7014", "dept": "태국파트", "leadTime": 72.0, "count": 2.0, "price": 879000.0, "dist": [0.0, 0.0, 100.0, 0.0, 0.0, 0.0, 0.0, 0.0]}, {"name": "APP7017", "dept": "태국파트", "leadTime": 109.7777777777778, "count": 9.0, "price": 918762.2222222222, "dist": [44.4, 0.0, 0.0, 0.0, 0.0, 0.0, 55.6, 0.0]}, {"name": "APP7020", "dept": "태국파트", "leadTime": 28.0, "count": 2.0, "price": 1069000.0, "dist": [100.0, 0.0, 0.0, 0.0, 0.0, 0.0, 0.0, 0.0]}, {"name": "APP7233", "dept": "동남아1팀", "leadTime": 38.0, "count": 4.0, "price": 869030.0, "dist": [50.0, 50.0, 0.0, 0.0, 0.0, 0.0, 0.0, 0.0]}, {"name": "APP7450", "dept": "필리핀/말레이시아파트", "leadTime": 79.0, "count": 5.0, "price": 499000.0, "dist": [0.0, 0.0, 100.0, 0.0, 0.0, 0.0, 0.0, 0.0]}, {"name": "APP7579", "dept": "동남아1팀", "leadTime": 44.0, "count": 2.0, "price": 599000.0, "dist": [0.0, 100.0, 0.0, 0.0, 0.0, 0.0, 0.0, 0.0]}, {"name": "APP7723", "dept": "필리핀/말레이시아파트", "leadTime": 41.0, "count": 2.0, "price": 999000.0, "dist": [0.0, 100.0, 0.0, 0.0, 0.0, 0.0, 0.0, 0.0]}, {"name": "APP7777", "dept": "동남아1팀", "leadTime": 28.0, "count": 1.0, "price": 1049000.0, "dist": [100.0, 0.0, 0.0, 0.0, 0.0, 0.0, 0.0, 0.0]}, {"name": "APP7811", "dept": "필리핀/말레이시아파트", "leadTime": 46.0, "count": 2.0, "price": 1329000.0, "dist": [0.0, 100.0, 0.0, 0.0, 0.0, 0.0, 0.0, 0.0]}, {"name": "APP8838", "dept": "동남아1팀", "leadTime": 39.44444444444444, "count": 18.0, "price": 716920.8888888889, "dist": [50.0, 22.2, 27.8, 0.0, 0.0, 0.0, 0.0, 0.0]}, {"name": "APP9523", "dept": "동남아1팀", "leadTime": 155.5555555555555, "count": 18.0, "price": 846222.2222222222, "dist": [0.0, 0.0, 0.0, 11.1, 0.0, 88.9, 0.0, 0.0]}, {"name": "APP9591", "dept": "부산지점", "leadTime": 24.0, "count": 2.0, "price": 739000.0, "dist": [100.0, 0.0, 0.0, 0.0, 0.0, 0.0, 0.0, 0.0]}, {"name": "APP9592", "dept": "부산지점", "leadTime": 105.0, "count": 3.0, "price": 1628630.0, "dist": [0.0, 0.0, 0.0, 100.0, 0.0, 0.0, 0.0, 0.0]}, {"name": "APP9933", "dept": "부산지점", "leadTime": 117.0, "count": 4.0, "price": 579000.0, "dist": [0.0, 0.0, 0.0, 100.0, 0.0, 0.0, 0.0, 0.0]}, {"name": "APP9945", "dept": "부산지점", "leadTime": 79.42857142857143, "count": 7.0, "price": 719112.8571428572, "dist": [0.0, 0.0, 100.0, 0.0, 0.0, 0.0, 0.0, 0.0]}, {"name": "APT333", "dept": "태국파트", "leadTime": 12.0, "count": 2.0, "price": 850000.0, "dist": [100.0, 0.0, 0.0, 0.0, 0.0, 0.0, 0.0, 0.0]}, {"name": "CPP1009", "dept": "중국팀", "leadTime": 38.28571428571428, "count": 7.0, "price": 1349000.0, "dist": [14.3, 85.7, 0.0, 0.0, 0.0, 0.0, 0.0, 0.0]}, {"name": "CPP163", "dept": "중국팀", "leadTime": 19.0, "count": 1.0, "price": 1299000.0, "dist": [100.0, 0.0, 0.0, 0.0, 0.0, 0.0, 0.0, 0.0]}, {"name": "CPP174", "dept": "중국팀", "leadTime": 152.0, "count": 6.0, "price": 1049000.0, "dist": [0.0, 0.0, 0.0, 0.0, 0.0, 100.0, 0.0, 0.0]}, {"name": "CPP230", "dept": "중국팀", "leadTime": 99.0, "count": 1.0, "price": 499000.0, "dist": [0.0, 0.0, 0.0, 100.0, 0.0, 0.0, 0.0, 0.0]}, {"name": "CPP254", "dept": "중국팀", "leadTime": 36.0, "count": 3.0, "price": 749000.0, "dist": [0.0, 100.0, 0.0, 0.0, 0.0, 0.0, 0.0, 0.0]}, {"name": "CPP255", "dept": "중국팀", "leadTime": 75.92, "count": 25.0, "price": 797000.0, "dist": [0.0, 20.0, 64.0, 16.0, 0.0, 0.0, 0.0, 0.0]}, {"name": "CPP256", "dept": "중국팀", "leadTime": 61.0, "count": 3.0, "price": 949000.0, "dist": [0.0, 0.0, 100.0, 0.0, 0.0, 0.0, 0.0, 0.0]}, {"name": "CPP258", "dept": "중국팀", "leadTime": 73.8, "count": 5.0, "price": 999000.0, "dist": [0.0, 0.0, 100.0, 0.0, 0.0, 0.0, 0.0, 0.0]}, {"name": "CPP2600", "dept": "중국팀", "leadTime": 45.54545454545455, "count": 22.0, "price": 828545.4545454546, "dist": [36.4, 31.8, 31.8, 0.0, 0.0, 0.0, 0.0, 0.0]}, {"name": "CPP2626", "dept": "중국팀", "leadTime": 63.58823529411764, "count": 17.0, "price": 1034294.117647059, "dist": [11.8, 11.8, 76.5, 0.0, 0.0, 0.0, 0.0, 0.0]}, {"name": "CPP284", "dept": "중국팀", "leadTime": 39.0, "count": 1.0, "price": 949000.0, "dist": [0.0, 100.0, 0.0, 0.0, 0.0, 0.0, 0.0, 0.0]}, {"name": "CPP286", "dept": "중국팀", "leadTime": 17.0, "count": 2.0, "price": 799000.0, "dist": [100.0, 0.0, 0.0, 0.0, 0.0, 0.0, 0.0, 0.0]}, {"name": "CPP322", "dept": "중국팀", "leadTime": 26.0, "count": 2.0, "price": 349000.0, "dist": [100.0, 0.0, 0.0, 0.0, 0.0, 0.0, 0.0, 0.0]}, {"name": "CPP3232", "dept": "중국팀", "leadTime": 67.42857142857143, "count": 14.0, "price": 984714.2857142857, "dist": [14.3, 0.0, 85.7, 0.0, 0.0, 0.0, 0.0, 0.0]}, {"name": "CPP3250", "dept": "중국팀", "leadTime": 52.4, "count": 5.0, "price": 859000.0, "dist": [0.0, 60.0, 40.0, 0.0, 0.0, 0.0, 0.0, 0.0]}, {"name": "CPP333", "dept": "중국팀", "leadTime": 66.0, "count": 4.0, "price": 1699000.0, "dist": [0.0, 50.0, 0.0, 50.0, 0.0, 0.0, 0.0, 0.0]}, {"name": "CPP334", "dept": "중국팀", "leadTime": 10.0, "count": 2.0, "price": 1399000.0, "dist": [100.0, 0.0, 0.0, 0.0, 0.0, 0.0, 0.0, 0.0]}, {"name": "CPP3400", "dept": "중국팀", "leadTime": 20.0, "count": 4.0, "price": 799000.0, "dist": [100.0, 0.0, 0.0, 0.0, 0.0, 0.0, 0.0, 0.0]}, {"name": "CPP375", "dept": "중국팀", "leadTime": 37.66666666666666, "count": 6.0, "price": 565666.6666666666, "dist": [33.3, 66.7, 0.0, 0.0, 0.0, 0.0, 0.0, 0.0]}, {"name": "CPP410", "dept": "중국팀", "leadTime": 90.44444444444444, "count": 18.0, "price": 782333.3333333334, "dist": [11.1, 0.0, 33.3, 0.0, 55.6, 0.0, 0.0, 0.0]}, {"name": "CPP421", "dept": "중국팀", "leadTime": 60.0, "count": 4.0, "price": 1324000.0, "dist": [25.0, 50.0, 0.0, 25.0, 0.0, 0.0, 0.0, 0.0]}, {"name": "CPP430", "dept": "중국팀", "leadTime": 18.0, "count": 2.0, "price": 649000.0, "dist": [100.0, 0.0, 0.0, 0.0, 0.0, 0.0, 0.0, 0.0]}, {"name": "CPP435", "dept": "중국팀", "leadTime": 40.0, "count": 2.0, "price": 1245000.0, "dist": [0.0, 100.0, 0.0, 0.0, 0.0, 0.0, 0.0, 0.0]}, {"name": "CPP4578", "dept": "중국팀", "leadTime": 49.16666666666666, "count": 12.0, "price": 382333.3333333333, "dist": [33.3, 33.3, 16.7, 16.7, 0.0, 0.0, 0.0, 0.0]}, {"name": "CPP475", "dept": "중국팀", "leadTime": 53.0, "count": 4.0, "price": 1149000.0, "dist": [0.0, 50.0, 50.0, 0.0, 0.0, 0.0, 0.0, 0.0]}, {"name": "CPP4763", "dept": "중국팀", "leadTime": 28.4, "count": 5.0, "price": 1571032.0, "dist": [60.0, 40.0, 0.0, 0.0, 0.0, 0.0, 0.0, 0.0]}, {"name": "CPP4777", "dept": "중국팀", "leadTime": 75.0, "count": 2.0, "price": 1299000.0, "dist": [0.0, 0.0, 100.0, 0.0, 0.0, 0.0, 0.0, 0.0]}, {"name": "CPP519", "dept": "중국팀", "leadTime": 31.0, "count": 5.0, "price": 309430.0, "dist": [0.0, 100.0, 0.0, 0.0, 0.0, 0.0, 0.0, 0.0]}, {"name": "CPP5252", "dept": "중국팀", "leadTime": 31.0, "count": 2.0, "price": 999000.0, "dist": [0.0, 100.0, 0.0, 0.0, 0.0, 0.0, 0.0, 0.0]}, {"name": "CPP551", "dept": "중국팀", "leadTime": 39.0, "count": 2.0, "price": 699000.0, "dist": [0.0, 100.0, 0.0, 0.0, 0.0, 0.0, 0.0, 0.0]}, {"name": "CPP5550", "dept": "대구지점", "leadTime": 43.0, "count": 4.0, "price": 999000.0, "dist": [0.0, 100.0, 0.0, 0.0, 0.0, 0.0, 0.0, 0.0]}, {"name": "CPP575", "dept": "중국팀", "leadTime": 130.0, "count": 6.0, "price": 2099000.0, "dist": [0.0, 0.0, 0.0, 0.0, 100.0, 0.0, 0.0, 0.0]}, {"name": "CPP7020", "dept": "대구지점", "leadTime": 22.0, "count": 2.0, "price": 1290000.0, "dist": [100.0, 0.0, 0.0, 0.0, 0.0, 0.0, 0.0, 0.0]}, {"name": "CPP7272", "dept": "중국팀", "leadTime": 51.33333333333334, "count": 6.0, "price": 949000.0, "dist": [33.3, 0.0, 66.7, 0.0, 0.0, 0.0, 0.0, 0.0]}, {"name": "CPP771", "dept": "중국팀", "leadTime": 119.0, "count": 11.0, "price": 449000.0, "dist": [0.0, 0.0, 0.0, 100.0, 0.0, 0.0, 0.0, 0.0]}, {"name": "CPP819", "dept": "부산지점", "leadTime": 57.66666666666666, "count": 6.0, "price": 1386510.0, "dist": [0.0, 33.3, 66.7, 0.0, 0.0, 0.0, 0.0, 0.0]}, {"name": "CPP843", "dept": "중국팀", "leadTime": 40.0, "count": 9.0, "price": 699000.0, "dist": [66.7, 0.0, 0.0, 33.3, 0.0, 0.0, 0.0, 0.0]}, {"name": "CPP845", "dept": "중국팀", "leadTime": 128.0, "count": 4.0, "price": 399000.0, "dist": [0.0, 0.0, 0.0, 0.0, 100.0, 0.0, 0.0, 0.0]}, {"name": "CPP919", "dept": "부산지점", "leadTime": 100.0, "count": 3.0, "price": 949000.0, "dist": [0.0, 0.0, 0.0, 100.0, 0.0, 0.0, 0.0, 0.0]}, {"name": "CPP929", "dept": "부산지점", "leadTime": 15.0, "count": 6.0, "price": 1042665.0, "dist": [100.0, 0.0, 0.0, 0.0, 0.0, 0.0, 0.0, 0.0]}, {"name": "CPP9376", "dept": "대구지점", "leadTime": 39.0, "count": 2.0, "price": 1806000.0, "dist": [0.0, 100.0, 0.0, 0.0, 0.0, 0.0, 0.0, 0.0]}, {"name": "CPP9684", "dept": "부산지점", "leadTime": 45.0, "count": 2.0, "price": 1039000.0, "dist": [0.0, 100.0, 0.0, 0.0, 0.0, 0.0, 0.0, 0.0]}, {"name": "CPP9802", "dept": "부산지점", "leadTime": 17.0, "count": 3.0, "price": 589000.0, "dist": [100.0, 0.0, 0.0, 0.0, 0.0, 0.0, 0.0, 0.0]}, {"name": "CPP985", "dept": "부산지점", "leadTime": 27.0, "count": 2.0, "price": 0.0, "dist": [100.0, 0.0, 0.0, 0.0, 0.0, 0.0, 0.0, 0.0]}, {"name": "CPP986", "dept": "부산지점", "leadTime": 71.66666666666667, "count": 9.0, "price": 1073444.444444444, "dist": [22.2, 0.0, 77.8, 0.0, 0.0, 0.0, 0.0, 0.0]}, {"name": "CPP988", "dept": "부산지점", "leadTime": 34.33333333333334, "count": 3.0, "price": 732333.3333333334, "dist": [0.0, 100.0, 0.0, 0.0, 0.0, 0.0, 0.0, 0.0]}, {"name": "CPP989", "dept": "부산지점", "leadTime": 39.0, "count": 4.0, "price": 1309000.0, "dist": [0.0, 100.0, 0.0, 0.0, 0.0, 0.0, 0.0, 0.0]}, {"name": "CPP9906", "dept": "부산지점", "leadTime": 42.66666666666666, "count": 3.0, "price": 1379000.0, "dist": [0.0, 100.0, 0.0, 0.0, 0.0, 0.0, 0.0, 0.0]}, {"name": "CPPT212", "dept": "대구지점", "leadTime": 21.0, "count": 2.0, "price": 899000.0, "dist": [100.0, 0.0, 0.0, 0.0, 0.0, 0.0, 0.0, 0.0]}, {"name": "CPPT311", "dept": "대구지점", "leadTime": 37.0, "count": 4.0, "price": 899000.0, "dist": [0.0, 100.0, 0.0, 0.0, 0.0, 0.0, 0.0, 0.0]}, {"name": "CPPT402", "dept": "대구지점", "leadTime": 41.0, "count": 1.0, "price": 1724000.0, "dist": [0.0, 100.0, 0.0, 0.0, 0.0, 0.0, 0.0, 0.0]}, {"name": "EPM017", "dept": "크루즈/테마팀", "leadTime": 103.0, "count": 2.0, "price": 7490000.0, "dist": [0.0, 0.0, 0.0, 100.0, 0.0, 0.0, 0.0, 0.0]}, {"name": "EPP011", "dept": "스페인/북유럽팀", "leadTime": 58.0, "count": 6.0, "price": 4223333.333333333, "dist": [0.0, 100.0, 0.0, 0.0, 0.0, 0.0, 0.0, 0.0]}, {"name": "EPP0112", "dept": "스페인/북유럽팀", "leadTime": 41.0, "count": 3.0, "price": 5390000.0, "dist": [0.0, 100.0, 0.0, 0.0, 0.0, 0.0, 0.0, 0.0]}, {"name": "EPP0114", "dept": "스페인/북유럽팀", "leadTime": 49.0, "count": 2.0, "price": 4490000.0, "dist": [0.0, 100.0, 0.0, 0.0, 0.0, 0.0, 0.0, 0.0]}, {"name": "EPP0211", "dept": "스페인/북유럽팀", "leadTime": 76.0, "count": 1.0, "price": 3690000.0, "dist": [0.0, 0.0, 100.0, 0.0, 0.0, 0.0, 0.0, 0.0]}, {"name": "EPP027", "dept": "스페인/북유럽팀", "leadTime": 54.66666666666666, "count": 15.0, "price": 5003333.333333333, "dist": [20.0, 40.0, 40.0, 0.0, 0.0, 0.0, 0.0, 0.0]}, {"name": "EPP129", "dept": "지중해/인도/아프리카팀", "leadTime": 179.0, "count": 4.0, "price": 3423333.333333333, "dist": [0.0, 0.0, 0.0, 0.0, 25.0, 50.0, 0.0, 25.0]}, {"name": "EPP200", "dept": "지중해/인도/아프리카팀", "leadTime": 95.5, "count": 8.0, "price": 1856142.857142857, "dist": [12.5, 12.5, 0.0, 25.0, 50.0, 0.0, 0.0, 0.0]}, {"name": "EPP207", "dept": "지중해/인도/아프리카팀", "leadTime": 145.0, "count": 1.0, "price": 0.0, "dist": [0.0, 0.0, 0.0, 0.0, 100.0, 0.0, 0.0, 0.0]}, {"name": "EPP208", "dept": "지중해/인도/아프리카팀", "leadTime": 50.77777777777778, "count": 9.0, "price": 1684714.285714286, "dist": [55.6, 0.0, 22.2, 22.2, 0.0, 0.0, 0.0, 0.0]}, {"name": "EPP2208", "dept": "지중해/인도/아프리카팀", "leadTime": 257.0, "count": 2.0, "price": 1649000.0, "dist": [0.0, 0.0, 0.0, 0.0, 0.0, 0.0, 0.0, 100.0]}, {"name": "EPP2510", "dept": "지중해/인도/아프리카팀", "leadTime": 89.0, "count": 4.0, "price": 0.0, "dist": [0.0, 50.0, 0.0, 0.0, 50.0, 0.0, 0.0, 0.0]}, {"name": "EPP2700", "dept": "지중해/인도/아프리카팀", "leadTime": 66.5, "count": 8.0, "price": 1549000.0, "dist": [0.0, 0.0, 100.0, 0.0, 0.0, 0.0, 0.0, 0.0]}, {"name": "EPP299", "dept": "지중해/인도/아프리카팀", "leadTime": 55.11111111111111, "count": 9.0, "price": 1149000.0, "dist": [11.1, 88.9, 0.0, 0.0, 0.0, 0.0, 0.0, 0.0]}, {"name": "EPP3097", "dept": "서유럽팀", "leadTime": 61.2, "count": 5.0, "price": 4650800.0, "dist": [0.0, 40.0, 60.0, 0.0, 0.0, 0.0, 0.0, 0.0]}, {"name": "EPP316", "dept": "서유럽팀", "leadTime": 53.09523809523809, "count": 21.0, "price": 4435952.380952381, "dist": [9.5, 61.9, 19.0, 9.5, 0.0, 0.0, 0.0, 0.0]}, {"name": "EPP3160", "dept": "서유럽팀", "leadTime": 80.0, "count": 4.0, "price": 3390000.0, "dist": [0.0, 0.0, 100.0, 0.0, 0.0, 0.0, 0.0, 0.0]}, {"name": "EPP3208", "dept": "프리미엄팀", "leadTime": 47.0, "count": 6.0, "price": 11590000.0, "dist": [0.0, 100.0, 0.0, 0.0, 0.0, 0.0, 0.0, 0.0]}, {"name": "EPP340", "dept": "서유럽팀", "leadTime": 41.25, "count": 8.0, "price": 3632420.0, "dist": [50.0, 25.0, 25.0, 0.0, 0.0, 0.0, 0.0, 0.0]}, {"name": "EPP3436", "dept": "서유럽팀", "leadTime": 135.0, "count": 2.0, "price": 4109000.0, "dist": [0.0, 0.0, 0.0, 0.0, 100.0, 0.0, 0.0, 0.0]}, {"name": "EPP3437", "dept": "서유럽팀", "leadTime": 76.125, "count": 8.0, "price": 2690000.0, "dist": [50.0, 0.0, 0.0, 0.0, 50.0, 0.0, 0.0, 0.0]}, {"name": "EPP3441", "dept": "서유럽팀", "leadTime": 156.0, "count": 13.0, "price": 4496153.846153846, "dist": [23.1, 0.0, 23.1, 0.0, 23.1, 0.0, 0.0, 30.8]}, {"name": "EPP3480", "dept": "서유럽팀", "leadTime": 303.0, "count": 12.0, "price": 3290000.0, "dist": [0.0, 0.0, 0.0, 0.0, 0.0, 0.0, 0.0, 100.0]}, {"name": "EPP3572", "dept": "서유럽팀", "leadTime": 141.3333333333333, "count": 6.0, "price": 2456666.666666667, "dist": [0.0, 0.0, 0.0, 0.0, 100.0, 0.0, 0.0, 0.0]}, {"name": "EPP3599", "dept": "서유럽팀", "leadTime": 76.0909090909091, "count": 11.0, "price": 2973745.454545455, "dist": [27.3, 0.0, 36.4, 18.2, 18.2, 0.0, 0.0, 0.0]}, {"name": "EPP3600", "dept": "서유럽팀", "leadTime": 39.25, "count": 8.0, "price": 7650500.0, "dist": [50.0, 25.0, 25.0, 0.0, 0.0, 0.0, 0.0, 0.0]}, {"name": "EPP3602", "dept": "서유럽팀", "leadTime": 42.0, "count": 3.0, "price": 3822266.666666667, "dist": [33.3, 66.7, 0.0, 0.0, 0.0, 0.0, 0.0, 0.0]}, {"name": "EPP3696", "dept": "서유럽팀", "leadTime": 29.0, "count": 3.0, "price": 4855000.0, "dist": [100.0, 0.0, 0.0, 0.0, 0.0, 0.0, 0.0, 0.0]}, {"name": "EPP3737", "dept": "서유럽팀", "leadTime": 18.0, "count": 2.0, "price": 3044000.0, "dist": [100.0, 0.0, 0.0, 0.0, 0.0, 0.0, 0.0, 0.0]}, {"name": "EPP3752", "dept": "서유럽팀", "leadTime": 86.0, "count": 2.0, "price": 2390000.0, "dist": [0.0, 0.0, 100.0, 0.0, 0.0, 0.0, 0.0, 0.0]}, {"name": "EPP3769", "dept": "서유럽팀", "leadTime": 15.0, "count": 2.0, "price": 0.0, "dist": [100.0, 0.0, 0.0, 0.0, 0.0, 0.0, 0.0, 0.0]}, {"name": "EPP3778", "dept": "서유럽팀", "leadTime": 32.0, "count": 1.0, "price": 5726800.0, "dist": [0.0, 100.0, 0.0, 0.0, 0.0, 0.0, 0.0, 0.0]}, {"name": "EPP3790", "dept": "서유럽팀", "leadTime": 165.4, "count": 10.0, "price": 3730000.0, "dist": [40.0, 0.0, 0.0, 0.0, 0.0, 20.0, 0.0, 40.0]}, {"name": "EPP3791", "dept": "서유럽팀", "leadTime": 205.0, "count": 2.0, "price": 0.0, "dist": [0.0, 0.0, 0.0, 0.0, 0.0, 0.0, 100.0, 0.0]}, {"name": "EPP3822", "dept": "서유럽팀", "leadTime": 67.0, "count": 5.0, "price": 3354180.0, "dist": [40.0, 0.0, 20.0, 40.0, 0.0, 0.0, 0.0, 0.0]}, {"name": "EPP3823", "dept": "서유럽팀", "leadTime": 278.0, "count": 2.0, "price": 4090000.0, "dist": [0.0, 0.0, 0.0, 0.0, 0.0, 0.0, 0.0, 100.0]}, {"name": "EPP3827", "dept": "서유럽팀", "leadTime": 145.0, "count": 5.0, "price": 3186000.0, "dist": [0.0, 0.0, 0.0, 0.0, 100.0, 0.0, 0.0, 0.0]}, {"name": "EPP385", "dept": "서유럽팀", "leadTime": 74.2, "count": 5.0, "price": 4786300.0, "dist": [0.0, 0.0, 100.0, 0.0, 0.0, 0.0, 0.0, 0.0]}, {"name": "EPP3872", "dept": "서유럽팀", "leadTime": 75.0, "count": 2.0, "price": 3890000.0, "dist": [0.0, 0.0, 100.0, 0.0, 0.0, 0.0, 0.0, 0.0]}, {"name": "EPP3950", "dept": "서유럽팀", "leadTime": 50.0, "count": 7.0, "price": 3190000.0, "dist": [0.0, 42.9, 57.1, 0.0, 0.0, 0.0, 0.0, 0.0]}, {"name": "EPP4057", "dept": "동유럽팀", "leadTime": 40.0, "count": 2.0, "price": 2444000.0, "dist": [0.0, 100.0, 0.0, 0.0, 0.0, 0.0, 0.0, 0.0]}, {"name": "EPP4067", "dept": "동유럽팀", "leadTime": 51.66666666666666, "count": 12.0, "price": 3709416.666666667, "dist": [0.0, 83.3, 16.7, 0.0, 0.0, 0.0, 0.0, 0.0]}, {"name": "EPP4101", "dept": "동유럽팀", "leadTime": 49.0, "count": 5.0, "price": 3945800.0, "dist": [0.0, 100.0, 0.0, 0.0, 0.0, 0.0, 0.0, 0.0]}, {"name": "EPP4102", "dept": "동유럽팀", "leadTime": 132.0, "count": 4.0, "price": 5009000.0, "dist": [0.0, 0.0, 0.0, 0.0, 100.0, 0.0, 0.0, 0.0]}, {"name": "EPP4117", "dept": "동유럽팀", "leadTime": 125.0, "count": 6.0, "price": 1960000.0, "dist": [0.0, 33.3, 0.0, 0.0, 0.0, 66.7, 0.0, 0.0]}, {"name": "EPP4119", "dept": "동유럽팀", "leadTime": 61.30769230769231, "count": 13.0, "price": 2477843.076923077, "dist": [15.4, 46.2, 15.4, 0.0, 23.1, 0.0, 0.0, 0.0]}, {"name": "EPP4180", "dept": "동유럽팀", "leadTime": 66.0, "count": 2.0, "price": 3791730.0, "dist": [0.0, 0.0, 100.0, 0.0, 0.0, 0.0, 0.0, 0.0]}, {"name": "EPP4190", "dept": "동유럽팀", "leadTime": 115.1111111111111, "count": 9.0, "price": 2932777.777777778, "dist": [0.0, 55.6, 0.0, 0.0, 0.0, 0.0, 44.4, 0.0]}, {"name": "EPP4220", "dept": "동유럽팀", "leadTime": 42.0, "count": 1.0, "price": 0.0, "dist": [0.0, 100.0, 0.0, 0.0, 0.0, 0.0, 0.0, 0.0]}, {"name": "EPP4224", "dept": "동유럽팀", "leadTime": 106.4, "count": 5.0, "price": 2644100.0, "dist": [0.0, 0.0, 20.0, 80.0, 0.0, 0.0, 0.0, 0.0]}, {"name": "EPP4270", "dept": "동유럽팀", "leadTime": 111.0, "count": 2.0, "price": 3609000.0, "dist": [0.0, 0.0, 0.0, 100.0, 0.0, 0.0, 0.0, 0.0]}, {"name": "EPP4337", "dept": "동유럽팀", "leadTime": 52.0, "count": 4.0, "price": 3709000.0, "dist": [0.0, 100.0, 0.0, 0.0, 0.0, 0.0, 0.0, 0.0]}, {"name": "EPP4338", "dept": "동유럽팀", "leadTime": 59.42857142857143, "count": 14.0, "price": 2579357.142857143, "dist": [42.9, 14.3, 0.0, 28.6, 14.3, 0.0, 0.0, 0.0]}, {"name": "EPP4350", "dept": "동유럽팀", "leadTime": 18.375, "count": 8.0, "price": 2551587.5, "dist": [100.0, 0.0, 0.0, 0.0, 0.0, 0.0, 0.0, 0.0]}, {"name": "EPP4390", "dept": "동유럽팀", "leadTime": 89.0, "count": 2.0, "price": 2576800.0, "dist": [0.0, 0.0, 100.0, 0.0, 0.0, 0.0, 0.0, 0.0]}, {"name": "EPP4534", "dept": "프리미엄팀", "leadTime": 54.0, "count": 2.0, "price": 8690000.0, "dist": [0.0, 100.0, 0.0, 0.0, 0.0, 0.0, 0.0, 0.0]}, {"name": "EPP4557", "dept": "동유럽팀", "leadTime": 24.375, "count": 8.0, "price": 3036250.0, "dist": [100.0, 0.0, 0.0, 0.0, 0.0, 0.0, 0.0, 0.0]}, {"name": "EPP456", "dept": "동유럽팀", "leadTime": 62.0, "count": 4.0, "price": 3855000.0, "dist": [0.0, 0.0, 100.0, 0.0, 0.0, 0.0, 0.0, 0.0]}, {"name": "EPP4568", "dept": "동유럽팀", "leadTime": 54.0, "count": 6.0, "price": 2861100.0, "dist": [33.3, 0.0, 66.7, 0.0, 0.0, 0.0, 0.0, 0.0]}, {"name": "EPP4580", "dept": "동유럽팀", "leadTime": 35.66666666666666, "count": 3.0, "price": 3255000.0, "dist": [0.0, 100.0, 0.0, 0.0, 0.0, 0.0, 0.0, 0.0]}, {"name": "EPP4585", "dept": "동유럽팀", "leadTime": 81.0, "count": 2.0, "price": 2190000.0, "dist": [0.0, 0.0, 100.0, 0.0, 0.0, 0.0, 0.0, 0.0]}, {"name": "EPP461", "dept": "동유럽팀", "leadTime": 14.0, "count": 1.0, "price": 0.0, "dist": [100.0, 0.0, 0.0, 0.0, 0.0, 0.0, 0.0, 0.0]}, {"name": "EPP4688", "dept": "동유럽팀", "leadTime": 37.0, "count": 2.0, "price": 4455000.0, "dist": [0.0, 100.0, 0.0, 0.0, 0.0, 0.0, 0.0, 0.0]}, {"name": "EPP4690", "dept": "동유럽팀", "leadTime": 122.0, "count": 2.0, "price": 3790000.0, "dist": [0.0, 0.0, 0.0, 0.0, 100.0, 0.0, 0.0, 0.0]}, {"name": "EPP4717", "dept": "동유럽팀", "leadTime": 106.188679245283, "count": 53.0, "price": 2350377.358490566, "dist": [13.2, 24.5, 11.3, 0.0, 11.3, 17.0, 22.6, 0.0]}, {"name": "EPP4779", "dept": "동유럽팀", "leadTime": 45.77777777777778, "count": 9.0, "price": 3115758.333333333, "dist": [55.6, 0.0, 44.4, 0.0, 0.0, 0.0, 0.0, 0.0]}, {"name": "EPP4790", "dept": "동유럽팀", "leadTime": 67.0, "count": 3.0, "price": 2538200.0, "dist": [0.0, 66.7, 33.3, 0.0, 0.0, 0.0, 0.0, 0.0]}, {"name": "EPP4889", "dept": "동유럽팀", "leadTime": 51.0, "count": 1.0, "price": 3555000.0, "dist": [0.0, 100.0, 0.0, 0.0, 0.0, 0.0, 0.0, 0.0]}, {"name": "EPP500", "dept": "스페인/북유럽팀", "leadTime": 258.0, "count": 2.0, "price": 2690000.0, "dist": [0.0, 0.0, 0.0, 0.0, 0.0, 0.0, 0.0, 100.0]}, {"name": "EPP5016", "dept": "스페인/북유럽팀", "leadTime": 79.0, "count": 2.0, "price": 3990000.0, "dist": [0.0, 0.0, 100.0, 0.0, 0.0, 0.0, 0.0, 0.0]}, {"name": "EPP5026", "dept": "지중해/인도/아프리카팀", "leadTime": 69.5, "count": 4.0, "price": 3590000.0, "dist": [0.0, 0.0, 100.0, 0.0, 0.0, 0.0, 0.0, 0.0]}, {"name": "EPP507", "dept": "스페인/북유럽팀", "leadTime": 80.0, "count": 6.0, "price": 2590000.0, "dist": [0.0, 33.3, 33.3, 33.3, 0.0, 0.0, 0.0, 0.0]}, {"name": "EPP511", "dept": "스페인/북유럽팀", "leadTime": 110.0, "count": 3.0, "price": 3044000.0, "dist": [0.0, 0.0, 0.0, 100.0, 0.0, 0.0, 0.0, 0.0]}, {"name": "EPP5405", "dept": "스페인/북유럽팀", "leadTime": 68.0, "count": 1.0, "price": 2490000.0, "dist": [0.0, 0.0, 100.0, 0.0, 0.0, 0.0, 0.0, 0.0]}, {"name": "EPP545", "dept": "스페인/북유럽팀", "leadTime": 40.0, "count": 5.0, "price": 1801800.0, "dist": [0.0, 100.0, 0.0, 0.0, 0.0, 0.0, 0.0, 0.0]}, {"name": "EPP553", "dept": "스페인/북유럽팀", "leadTime": 80.25, "count": 8.0, "price": 2468325.0, "dist": [25.0, 0.0, 25.0, 50.0, 0.0, 0.0, 0.0, 0.0]}, {"name": "EPP554", "dept": "스페인/북유럽팀", "leadTime": 122.0, "count": 4.0, "price": 2340000.0, "dist": [0.0, 0.0, 50.0, 0.0, 0.0, 50.0, 0.0, 0.0]}, {"name": "EPP5648", "dept": "스페인/북유럽팀", "leadTime": 98.2, "count": 5.0, "price": 4690000.0, "dist": [0.0, 0.0, 40.0, 60.0, 0.0, 0.0, 0.0, 0.0]}, {"name": "EPP5744", "dept": "지중해/인도/아프리카팀", "leadTime": 71.0, "count": 2.0, "price": 3590000.0, "dist": [0.0, 0.0, 100.0, 0.0, 0.0, 0.0, 0.0, 0.0]}, {"name": "EPP5746", "dept": "지중해/인도/아프리카팀", "leadTime": 67.0, "count": 2.0, "price": 3990000.0, "dist": [0.0, 0.0, 100.0, 0.0, 0.0, 0.0, 0.0, 0.0]}, {"name": "FPP153", "dept": "지중해/인도/아프리카팀", "leadTime": 116.0, "count": 2.0, "price": 5690000.0, "dist": [0.0, 50.0, 0.0, 0.0, 0.0, 0.0, 50.0, 0.0]}, {"name": "FPP155", "dept": "지중해/인도/아프리카팀", "leadTime": 141.0, "count": 2.0, "price": 3490000.0, "dist": [0.0, 0.0, 0.0, 0.0, 100.0, 0.0, 0.0, 0.0]}, {"name": "IPF360", "dept": "남태평양팀", "leadTime": 27.0, "count": 3.0, "price": 1137163.333333333, "dist": [100.0, 0.0, 0.0, 0.0, 0.0, 0.0, 0.0, 0.0]}, {"name": "JFF822", "dept": "부산지점", "leadTime": 25.6, "count": 10.0, "price": 447000.0, "dist": [100.0, 0.0, 0.0, 0.0, 0.0, 0.0, 0.0, 0.0]}, {"name": "JPC945", "dept": "부산지점", "leadTime": 47.0, "count": 1.0, "price": 459000.0, "dist": [0.0, 100.0, 0.0, 0.0, 0.0, 0.0, 0.0, 0.0]}, {"name": "JPC953", "dept": "부산지점", "leadTime": 48.0, "count": 2.0, "price": 217000.0, "dist": [0.0, 100.0, 0.0, 0.0, 0.0, 0.0, 0.0, 0.0]}, {"name": "JPP016", "dept": "일본팀", "leadTime": 90.66666666666667, "count": 6.0, "price": 1697053.333333333, "dist": [0.0, 33.3, 0.0, 66.7, 0.0, 0.0, 0.0, 0.0]}, {"name": "JPP0166", "dept": "일본팀", "leadTime": 44.0, "count": 1.0, "price": 2149000.0, "dist": [0.0, 100.0, 0.0, 0.0, 0.0, 0.0, 0.0, 0.0]}, {"name": "JPP018", "dept": "일본팀", "leadTime": 45.0, "count": 9.0, "price": 1493444.444444444, "dist": [44.4, 33.3, 0.0, 22.2, 0.0, 0.0, 0.0, 0.0]}, {"name": "JPP019", "dept": "일본팀", "leadTime": 45.2741935483871, "count": 62.0, "price": 1373403.333333333, "dist": [27.4, 51.6, 16.1, 0.0, 4.8, 0.0, 0.0, 0.0]}, {"name": "JPP023", "dept": "일본팀", "leadTime": 10.0, "count": 2.0, "price": 1299000.0, "dist": [100.0, 0.0, 0.0, 0.0, 0.0, 0.0, 0.0, 0.0]}, {"name": "JPP025", "dept": "일본팀", "leadTime": 40.09090909090909, "count": 22.0, "price": 1319311.363636364, "dist": [27.3, 63.6, 0.0, 9.1, 0.0, 0.0, 0.0, 0.0]}, {"name": "JPP026", "dept": "일본팀", "leadTime": 22.10714285714286, "count": 28.0, "price": 1300785.714285714, "dist": [92.9, 7.1, 0.0, 0.0, 0.0, 0.0, 0.0, 0.0]}, {"name": "JPP0808", "dept": "일본팀", "leadTime": 56.0, "count": 7.0, "price": 1970442.857142857, "dist": [0.0, 100.0, 0.0, 0.0, 0.0, 0.0, 0.0, 0.0]}, {"name": "JPP088", "dept": "일본팀", "leadTime": 32.55882352941177, "count": 34.0, "price": 1594140.588235294, "dist": [35.3, 64.7, 0.0, 0.0, 0.0, 0.0, 0.0, 0.0]}, {"name": "JPP4066", "dept": "일본팀", "leadTime": 34.0, "count": 2.0, "price": 969030.0, "dist": [0.0, 100.0, 0.0, 0.0, 0.0, 0.0, 0.0, 0.0]}, {"name": "JPP423", "dept": "일본팀", "leadTime": 56.75, "count": 16.0, "price": 836512.5, "dist": [25.0, 0.0, 75.0, 0.0, 0.0, 0.0, 0.0, 0.0]}, {"name": "JPP433", "dept": "일본팀", "leadTime": 33.0, "count": 3.0, "price": 1099000.0, "dist": [0.0, 100.0, 0.0, 0.0, 0.0, 0.0, 0.0, 0.0]}, {"name": "JPP488", "dept": "일본팀", "leadTime": 45.0, "count": 2.0, "price": 849000.0, "dist": [0.0, 100.0, 0.0, 0.0, 0.0, 0.0, 0.0, 0.0]}, {"name": "JPP4881", "dept": "일본팀", "leadTime": 125.0, "count": 3.0, "price": 1199000.0, "dist": [0.0, 0.0, 0.0, 0.0, 100.0, 0.0, 0.0, 0.0]}, {"name": "JPP565", "dept": "일본팀", "leadTime": 81.0, "count": 5.0, "price": 1129000.0, "dist": [40.0, 0.0, 0.0, 0.0, 60.0, 0.0, 0.0, 0.0]}, {"name": "JPP617", "dept": "일본팀", "leadTime": 17.5, "count": 4.0, "price": 699000.0, "dist": [100.0, 0.0, 0.0, 0.0, 0.0, 0.0, 0.0, 0.0]}, {"name": "JPP619", "dept": "일본팀", "leadTime": 39.0, "count": 2.0, "price": 996550.0, "dist": [0.0, 100.0, 0.0, 0.0, 0.0, 0.0, 0.0, 0.0]}, {"name": "JPP640", "dept": "일본팀", "leadTime": 25.0, "count": 2.0, "price": 799000.0, "dist": [100.0, 0.0, 0.0, 0.0, 0.0, 0.0, 0.0, 0.0]}, {"name": "JPP646", "dept": "일본팀", "leadTime": 163.0, "count": 10.0, "price": 1399000.0, "dist": [0.0, 0.0, 0.0, 0.0, 0.0, 100.0, 0.0, 0.0]}, {"name": "JPP647", "dept": "일본팀", "leadTime": 118.0, "count": 3.0, "price": 1049000.0, "dist": [0.0, 0.0, 0.0, 100.0, 0.0, 0.0, 0.0, 0.0]}, {"name": "JPP649", "dept": "일본팀", "leadTime": 37.875, "count": 8.0, "price": 1055250.0, "dist": [37.5, 62.5, 0.0, 0.0, 0.0, 0.0, 0.0, 0.0]}, {"name": "JPP655", "dept": "일본팀", "leadTime": 23.0, "count": 4.0, "price": 799000.0, "dist": [100.0, 0.0, 0.0, 0.0, 0.0, 0.0, 0.0, 0.0]}, {"name": "JPP6610", "dept": "일본팀", "leadTime": 34.41666666666666, "count": 12.0, "price": 779833.3333333334, "dist": [25.0, 75.0, 0.0, 0.0, 0.0, 0.0, 0.0, 0.0]}, {"name": "JPP6644", "dept": "일본팀", "leadTime": 47.24137931034483, "count": 29.0, "price": 867965.5172413794, "dist": [31.0, 41.4, 13.8, 13.8, 0.0, 0.0, 0.0, 0.0]}, {"name": "JPP6690", "dept": "일본팀", "leadTime": 16.0, "count": 2.0, "price": 872030.0, "dist": [100.0, 0.0, 0.0, 0.0, 0.0, 0.0, 0.0, 0.0]}, {"name": "JPP7000", "dept": "일본팀", "leadTime": 40.0, "count": 6.0, "price": 1199000.0, "dist": [0.0, 100.0, 0.0, 0.0, 0.0, 0.0, 0.0, 0.0]}, {"name": "JPP708", "dept": "일본팀", "leadTime": 178.0, "count": 3.0, "price": 1599000.0, "dist": [0.0, 0.0, 0.0, 0.0, 0.0, 100.0, 0.0, 0.0]}, {"name": "JPP710", "dept": "일본팀", "leadTime": 19.0, "count": 5.0, "price": 1399000.0, "dist": [100.0, 0.0, 0.0, 0.0, 0.0, 0.0, 0.0, 0.0]}, {"name": "JPP712", "dept": "일본팀", "leadTime": 54.5, "count": 12.0, "price": 826272.7272727273, "dist": [8.3, 50.0, 33.3, 8.3, 0.0, 0.0, 0.0, 0.0]}, {"name": "JPP7707", "dept": "일본팀", "leadTime": 41.0, "count": 2.0, "price": 1349000.0, "dist": [0.0, 100.0, 0.0, 0.0, 0.0, 0.0, 0.0, 0.0]}, {"name": "JPP821", "dept": "부산지점", "leadTime": 21.92857142857143, "count": 14.0, "price": 625217.8571428572, "dist": [100.0, 0.0, 0.0, 0.0, 0.0, 0.0, 0.0, 0.0]}, {"name": "JPP829", "dept": "부산지점", "leadTime": 12.0, "count": 3.0, "price": 593000.0, "dist": [100.0, 0.0, 0.0, 0.0, 0.0, 0.0, 0.0, 0.0]}, {"name": "JPP842", "dept": "부산지점", "leadTime": 25.5, "count": 8.0, "price": 1661000.0, "dist": [100.0, 0.0, 0.0, 0.0, 0.0, 0.0, 0.0, 0.0]}, {"name": "JPP944", "dept": "부산지점", "leadTime": 41.8, "count": 10.0, "price": 917934.0, "dist": [40.0, 40.0, 20.0, 0.0, 0.0, 0.0, 0.0, 0.0]}, {"name": "JPP954", "dept": "부산지점", "leadTime": 44.0, "count": 4.0, "price": 885000.0, "dist": [0.0, 100.0, 0.0, 0.0, 0.0, 0.0, 0.0, 0.0]}, {"name": "JPPT101", "dept": "대구지점", "leadTime": 43.0, "count": 4.0, "price": 1050510.0, "dist": [0.0, 100.0, 0.0, 0.0, 0.0, 0.0, 0.0, 0.0]}, {"name": "JPPT501", "dept": "대구지점", "leadTime": 43.0, "count": 8.0, "price": 311000.0, "dist": [0.0, 100.0, 0.0, 0.0, 0.0, 0.0, 0.0, 0.0]}, {"name": "JPPT511", "dept": "대구지점", "leadTime": 32.0, "count": 3.0, "price": 392333.3333333333, "dist": [0.0, 100.0, 0.0, 0.0, 0.0, 0.0, 0.0, 0.0]}, {"name": "KFF207", "dept": "국내팀", "leadTime": 23.0, "count": 2.0, "price": 490000.0, "dist": [100.0, 0.0, 0.0, 0.0, 0.0, 0.0, 0.0, 0.0]}, {"name": "KPI115", "dept": "국내팀", "leadTime": 58.0, "count": 4.0, "price": 189000.0, "dist": [0.0, 100.0, 0.0, 0.0, 0.0, 0.0, 0.0, 0.0]}, {"name": "KPI120", "dept": "국내팀", "leadTime": 12.0, "count": 1.0, "price": 0.0, "dist": [100.0, 0.0, 0.0, 0.0, 0.0, 0.0, 0.0, 0.0]}, {"name": "KPI400", "dept": "국내팀", "leadTime": 23.4, "count": 5.0, "price": 433333.3333333333, "dist": [80.0, 0.0, 20.0, 0.0, 0.0, 0.0, 0.0, 0.0]}, {"name": "KPP324", "dept": "국내팀", "leadTime": 59.0, "count": 2.0, "price": 0.0, "dist": [0.0, 100.0, 0.0, 0.0, 0.0, 0.0, 0.0, 0.0]}, {"name": "KPP3778", "dept": "국내팀", "leadTime": 59.0, "count": 2.0, "price": 780000.0, "dist": [0.0, 100.0, 0.0, 0.0, 0.0, 0.0, 0.0, 0.0]}, {"name": "KPP502", "dept": "국내팀", "leadTime": 59.0, "count": 2.0, "price": 0.0, "dist": [0.0, 100.0, 0.0, 0.0, 0.0, 0.0, 0.0, 0.0]}, {"name": "KPP545", "dept": "국내팀", "leadTime": 59.0, "count": 2.0, "price": 0.0, "dist": [0.0, 100.0, 0.0, 0.0, 0.0, 0.0, 0.0, 0.0]}, {"name": "KPP811", "dept": "국내팀", "leadTime": 59.0, "count": 2.0, "price": 0.0, "dist": [0.0, 100.0, 0.0, 0.0, 0.0, 0.0, 0.0, 0.0]}, {"name": "KPP813", "dept": "국내팀", "leadTime": 59.0, "count": 2.0, "price": 0.0, "dist": [0.0, 100.0, 0.0, 0.0, 0.0, 0.0, 0.0, 0.0]}, {"name": "KPP912", "dept": "국내팀", "leadTime": 59.0, "count": 2.0, "price": 0.0, "dist": [0.0, 100.0, 0.0, 0.0, 0.0, 0.0, 0.0, 0.0]}, {"name": "KPP915", "dept": "국내팀", "leadTime": 59.0, "count": 4.0, "price": 470000.0, "dist": [0.0, 100.0, 0.0, 0.0, 0.0, 0.0, 0.0, 0.0]}, {"name": "KPP918", "dept": "국내팀", "leadTime": 59.0, "count": 2.0, "price": 0.0, "dist": [0.0, 100.0, 0.0, 0.0, 0.0, 0.0, 0.0, 0.0]}, {"name": "MPP900", "dept": "지중해/인도/아프리카팀", "leadTime": 48.0, "count": 2.0, "price": 2249000.0, "dist": [0.0, 100.0, 0.0, 0.0, 0.0, 0.0, 0.0, 0.0]}, {"name": "MPP947", "dept": "지중해/인도/아프리카팀", "leadTime": 30.0, "count": 2.0, "price": 774500.0, "dist": [100.0, 0.0, 0.0, 0.0, 0.0, 0.0, 0.0, 0.0]}, {"name": "PPP212", "dept": "남태평양팀", "leadTime": 22.5, "count": 4.0, "price": 1536500.0, "dist": [100.0, 0.0, 0.0, 0.0, 0.0, 0.0, 0.0, 0.0]}, {"name": "PPP236", "dept": "남태평양팀", "leadTime": 55.0, "count": 4.0, "price": 1799000.0, "dist": [0.0, 100.0, 0.0, 0.0, 0.0, 0.0, 0.0, 0.0]}, {"name": "PPP282", "dept": "남태평양팀", "leadTime": 144.0, "count": 2.0, "price": 1249000.0, "dist": [0.0, 0.0, 0.0, 0.0, 100.0, 0.0, 0.0, 0.0]}, {"name": "PPP340", "dept": "남태평양팀", "leadTime": 77.0, "count": 2.0, "price": 4390000.0, "dist": [0.0, 0.0, 100.0, 0.0, 0.0, 0.0, 0.0, 0.0]}, {"name": "PPP803", "dept": "남태평양팀", "leadTime": 83.0, "count": 2.0, "price": 4190000.0, "dist": [0.0, 0.0, 100.0, 0.0, 0.0, 0.0, 0.0, 0.0]}, {"name": "PPP888", "dept": "남태평양팀", "leadTime": 131.0, "count": 1.0, "price": 3590000.0, "dist": [0.0, 0.0, 0.0, 0.0, 100.0, 0.0, 0.0, 0.0]}, {"name": "UPM002", "dept": "크루즈/테마팀", "leadTime": 285.0, "count": 4.0, "price": 6490000.0, "dist": [0.0, 0.0, 0.0, 0.0, 0.0, 0.0, 0.0, 100.0]}, {"name": "UPP156", "dept": "미주팀", "leadTime": 58.5, "count": 4.0, "price": 3312000.0, "dist": [0.0, 50.0, 50.0, 0.0, 0.0, 0.0, 0.0, 0.0]}, {"name": "UPP223", "dept": "미주팀", "leadTime": 96.71428571428571, "count": 7.0, "price": 3682857.142857143, "dist": [0.0, 0.0, 57.1, 42.9, 0.0, 0.0, 0.0, 0.0]}, {"name": "UPP3281", "dept": "미주팀", "leadTime": 88.0, "count": 3.0, "price": 3956666.666666667, "dist": [0.0, 0.0, 66.7, 0.0, 33.3, 0.0, 0.0, 0.0]}, {"name": "UPP3824", "dept": "미주팀", "leadTime": 126.0, "count": 2.0, "price": 4590000.0, "dist": [0.0, 0.0, 0.0, 0.0, 100.0, 0.0, 0.0, 0.0]}, {"name": "UPP3982", "dept": "미주팀", "leadTime": 90.0, "count": 2.0, "price": 4670000.0, "dist": [0.0, 0.0, 100.0, 0.0, 0.0, 0.0, 0.0, 0.0]}, {"name": "UPP3986", "dept": "미주팀", "leadTime": 39.0, "count": 4.0, "price": 5090000.0, "dist": [0.0, 100.0, 0.0, 0.0, 0.0, 0.0, 0.0, 0.0]}, {"name": "UPP452", "dept": "미주팀", "leadTime": 66.5, "count": 4.0, "price": 2040000.0, "dist": [50.0, 0.0, 0.0, 50.0, 0.0, 0.0, 0.0, 0.0]}, {"name": "UPP601", "dept": "미주팀", "leadTime": 21.0, "count": 3.0, "price": 30000.0, "dist": [100.0, 0.0, 0.0, 0.0, 0.0, 0.0, 0.0, 0.0]}, {"name": "UPP604", "dept": "미주팀", "leadTime": 21.0, "count": 1.0, "price": 30000.0, "dist": [100.0, 0.0, 0.0, 0.0, 0.0, 0.0, 0.0, 0.0]}, {"name": "UPP665", "dept": "미주팀", "leadTime": 201.0, "count": 3.0, "price": 13990000.0, "dist": [0.0, 0.0, 0.0, 0.0, 33.3, 0.0, 0.0, 66.7]}, {"name": "ZPP2077", "dept": "중국팀", "leadTime": 63.0, "count": 2.0, "price": 3990000.0, "dist": [0.0, 0.0, 100.0, 0.0, 0.0, 0.0, 0.0, 0.0]}, {"name": "ZPP7875", "dept": "중국팀", "leadTime": 64.0, "count": 1.0, "price": 1999000.0, "dist": [0.0, 0.0, 100.0, 0.0, 0.0, 0.0, 0.0, 0.0]}], "price": [{"name": "100~200만 미만", "leadTime": 57.9, "count": 420.0, "price": 0.0, "dist": [28.8, 41.4, 9.0, 9.5, 3.6, 7.1, 0.0, 0.5]}, {"name": "200~300만 미만", "leadTime": 86.68367346938776, "count": 196.0, "price": 0.0, "dist": [20.4, 19.9, 19.9, 8.2, 14.8, 7.7, 8.2, 1.0]}, {"name": "300만~", "leadTime": 92.82264150943396, "count": 265.0, "price": 0.0, "dist": [12.8, 30.2, 27.5, 7.9, 9.1, 1.5, 0.4, 10.6]}, {"name": "50~100만 미만", "leadTime": 53.77723577235772, "count": 615.0, "price": 0.0, "dist": [32.0, 28.1, 28.6, 5.7, 2.1, 2.6, 0.8, 0.0]}, {"name": "50만 미만", "leadTime": 50.39428571428572, "count": 175.0, "price": 0.0, "dist": [38.3, 32.0, 14.9, 12.6, 2.3, 0.0, 0.0, 0.0]}]}